{"builtAtIso":"2026-05-25T02:52:23.384Z","minConviction":3,"picks":[{"symbol":"ASTS","side":"call","score":4,"conviction":4,"compositeScore":3.68,"thesis":"Bullish setup on ASTS: 8-day green run (+38.6%); MACD above signal (bullish).","drivers":[{"tag":"streak","weight":3,"text":"8-day green run (+38.6%)"},{"tag":"macd","weight":1,"text":"MACD above signal (bullish)"}],"spot":105.86,"sector":"Technology","sentiment":null,"fundamentalsVerdict":null,"rsi":67.94,"ivPctile":47,"streak":{"color":"green","days":8,"cumulativePct":38.64191027693478},"contract":{"strike":125,"expiry":1784246400,"expiryLabel":"Jul 16 '26","dte":53,"bid":11.6,"ask":12,"mid":11.8,"last":11.69,"iv":1.1365,"oi":1595,"volume":746,"delta":0.439,"thetaDay":-0.1751,"breakeven":136.8,"breakevenMovePct":29.23,"expectedMovePct":43.26,"rrRatio":0.68,"extrinsicRatio":1,"earningsInWindow":false,"contractQuality":{"spread":{"cls":"good","label":"Tight"},"oi":{"cls":"good","label":"Liquid"},"delta":{"cls":"good","label":"Balanced"},"theta":{"cls":"fair","label":"Normal"},"iv":{"cls":"fair","label":"Normal"},"overall":"fair"},"qualityScore":0.92}},{"symbol":"PLTR","side":"call","score":4,"conviction":4,"compositeScore":3.588,"thesis":"Bullish setup on PLTR: 7-day green run (+5.2%); MACD above signal (bullish).","drivers":[{"tag":"streak","weight":3,"text":"7-day green run (+5.2%)"},{"tag":"macd","weight":1,"text":"MACD above signal (bullish)"}],"spot":136.88,"sector":"Technology","sentiment":null,"fundamentalsVerdict":null,"rsi":47.49,"ivPctile":24,"streak":{"color":"green","days":7,"cumulativePct":5.1723696959812},"contract":{"strike":145,"expiry":1784246400,"expiryLabel":"Jul 16 '26","dte":53,"bid":6.5,"ask":6.65,"mid":6.58,"last":6.57,"iv":0.4724,"oi":6934,"volume":488,"delta":0.423,"thetaDay":-0.0974,"breakeven":151.57,"breakevenMovePct":10.74,"expectedMovePct":17.98,"rrRatio":0.6,"extrinsicRatio":1,"earningsInWindow":false,"contractQuality":{"spread":{"cls":"good","label":"Tight"},"oi":{"cls":"good","label":"Liquid"},"delta":{"cls":"good","label":"Balanced"},"theta":{"cls":"fair","label":"Normal"},"iv":{"cls":"good","label":"Calm"},"overall":"fair"},"qualityScore":0.897}},{"symbol":"U","side":"put","score":-4,"conviction":4,"compositeScore":3.488,"thesis":"Bearish setup on U: 6-day red run (-6.4%); MACD below signal (bearish).","drivers":[{"tag":"streak","weight":-3,"text":"6-day red run (-6.4%)"},{"tag":"macd","weight":-1,"text":"MACD below signal (bearish)"}],"spot":25.57,"sector":"Technology","sentiment":null,"fundamentalsVerdict":null,"rsi":47.55,"ivPctile":16,"streak":{"color":"red","days":6,"cumulativePct":-6.4027803163982835},"contract":{"strike":25,"expiry":1784246400,"expiryLabel":"Jul 16 '26","dte":53,"bid":2.09,"ask":2.16,"mid":2.13,"last":2.33,"iv":0.6201,"oi":501,"volume":15,"delta":-0.405,"thetaDay":-0.0206,"breakeven":22.88,"breakevenMovePct":10.54,"expectedMovePct":23.6,"rrRatio":0.45,"extrinsicRatio":1,"earningsInWindow":false,"contractQuality":{"spread":{"cls":"good","label":"Tight"},"oi":{"cls":"good","label":"Liquid"},"delta":{"cls":"good","label":"Balanced"},"theta":{"cls":"good","label":"Slow"},"iv":{"cls":"good","label":"Calm"},"overall":"good"},"qualityScore":0.872}},{"symbol":"APO","side":"put","score":-4,"conviction":4,"compositeScore":3.42,"thesis":"Bearish setup on APO: 6-day red run (-5.3%); MACD below signal (bearish).","drivers":[{"tag":"streak","weight":-3,"text":"6-day red run (-5.3%)"},{"tag":"macd","weight":-1,"text":"MACD below signal (bearish)"}],"spot":128.51,"sector":"Financial Services","sentiment":null,"fundamentalsVerdict":null,"rsi":51.6,"ivPctile":48,"streak":{"color":"red","days":6,"cumulativePct":-5.256947168810363},"contract":{"strike":130,"expiry":1784246400,"expiryLabel":"Jul 16 '26","dte":53,"bid":7.4,"ask":7.8,"mid":7.6,"last":7.3,"iv":0.3547,"oi":434,"volume":4,"delta":-0.488,"thetaDay":-0.0568,"breakeven":122.4,"breakevenMovePct":4.75,"expectedMovePct":13.5,"rrRatio":0.35,"extrinsicRatio":0.8,"earningsInWindow":false,"contractQuality":{"spread":{"cls":"good","label":"Tight"},"oi":{"cls":"fair","label":"Light"},"delta":{"cls":"good","label":"Balanced"},"theta":{"cls":"good","label":"Slow"},"iv":{"cls":"fair","label":"Normal"},"overall":"fair"},"qualityScore":0.855}},{"symbol":"DE","side":"put","score":-4,"conviction":4,"compositeScore":3.128,"thesis":"Bearish setup on DE: 8-day red run (-10.6%); MACD below signal (bearish).","drivers":[{"tag":"streak","weight":-3,"text":"8-day red run (-10.6%)"},{"tag":"macd","weight":-1,"text":"MACD below signal (bearish)"}],"spot":529.15,"sector":"Industrials","sentiment":null,"fundamentalsVerdict":null,"rsi":32.92,"ivPctile":62,"streak":{"color":"red","days":8,"cumulativePct":-10.557294553014794},"contract":{"strike":520,"expiry":1784246400,"expiryLabel":"Jul 16 '26","dte":53,"bid":17.3,"ask":19,"mid":18.15,"last":18.25,"iv":0.2895,"oi":221,"volume":38,"delta":-0.393,"thetaDay":-0.1843,"breakeven":501.85,"breakevenMovePct":5.16,"expectedMovePct":11.02,"rrRatio":0.47,"extrinsicRatio":1,"earningsInWindow":false,"contractQuality":{"spread":{"cls":"fair","label":"OK"},"oi":{"cls":"fair","label":"Light"},"delta":{"cls":"fair","label":"Skewed"},"theta":{"cls":"good","label":"Slow"},"iv":{"cls":"fair","label":"Normal"},"overall":"fair"},"qualityScore":0.782}},{"symbol":"ACN","side":"call","score":4,"conviction":4,"compositeScore":3.024,"thesis":"Bullish setup on ACN: 7-day green run (+11.8%); MACD above signal (bullish).","drivers":[{"tag":"streak","weight":3,"text":"7-day green run (+11.8%)"},{"tag":"macd","weight":1,"text":"MACD above signal (bullish)"}],"spot":179.24,"sector":"Technology","sentiment":null,"fundamentalsVerdict":null,"rsi":49.57,"ivPctile":66,"streak":{"color":"green","days":7,"cumulativePct":11.80469763210811},"contract":{"strike":190,"expiry":1784246400,"expiryLabel":"Jul 16 '26","dte":53,"bid":8.3,"ask":9.4,"mid":8.85,"last":9,"iv":0.4998,"oi":511,"volume":33,"delta":0.43,"thetaDay":-0.135,"breakeven":198.85,"breakevenMovePct":10.94,"expectedMovePct":19.02,"rrRatio":0.58,"extrinsicRatio":1,"earningsInWindow":true,"contractQuality":{"spread":{"cls":"fair","label":"OK"},"oi":{"cls":"good","label":"Liquid"},"delta":{"cls":"good","label":"Balanced"},"theta":{"cls":"fair","label":"Normal"},"iv":{"cls":"fair","label":"Normal"},"overall":"fair"},"qualityScore":0.756}},{"symbol":"GOOGL","side":"put","score":-3,"conviction":3,"compositeScore":2.787,"thesis":"Bearish setup on GOOGL: 7-day red run (-5.0%); MACD below signal (bearish); IV elevated (92th %ile) — expensive premium.","drivers":[{"tag":"streak","weight":-3,"text":"7-day red run (-5.0%)"},{"tag":"macd","weight":-1,"text":"MACD below signal (bearish)"},{"tag":"iv","weight":1,"text":"IV elevated (92th %ile) — expensive premium"}],"spot":382.97,"sector":"Communication Services","sentiment":null,"fundamentalsVerdict":null,"rsi":57.49,"ivPctile":92,"streak":{"color":"red","days":7,"cumulativePct":-4.9609624295064485},"contract":{"strike":380,"expiry":1784246400,"expiryLabel":"Jul 16 '26","dte":53,"bid":15.5,"ask":16,"mid":15.75,"last":15.51,"iv":0.2982,"oi":1553,"volume":161,"delta":-0.427,"thetaDay":-0.1393,"breakeven":364.25,"breakevenMovePct":4.89,"expectedMovePct":11.35,"rrRatio":0.43,"extrinsicRatio":1,"earningsInWindow":false,"contractQuality":{"spread":{"cls":"good","label":"Tight"},"oi":{"cls":"good","label":"Liquid"},"delta":{"cls":"good","label":"Balanced"},"theta":{"cls":"good","label":"Slow"},"iv":{"cls":"bad","label":"Elevated"},"overall":"good"},"qualityScore":0.929}},{"symbol":"V","side":"call","score":3,"conviction":3,"compositeScore":2.649,"thesis":"Bullish setup on V: 7-day green run (+2.7%); MACD above signal (bullish); IV elevated (86th %ile) — expensive premium.","drivers":[{"tag":"streak","weight":3,"text":"7-day green run (+2.7%)"},{"tag":"macd","weight":1,"text":"MACD above signal (bullish)"},{"tag":"iv","weight":-1,"text":"IV elevated (86th %ile) — expensive premium"}],"spot":328.88,"sector":"Financial Services","sentiment":null,"fundamentalsVerdict":null,"rsi":57.78,"ivPctile":86,"streak":{"color":"green","days":7,"cumulativePct":2.6758490860377453},"contract":{"strike":335,"expiry":1784246400,"expiryLabel":"Jul 16 '26","dte":53,"bid":8.8,"ask":9.3,"mid":9.05,"last":9.35,"iv":0.2379,"oi":523,"volume":47,"delta":0.466,"thetaDay":-0.1296,"breakeven":344.05,"breakevenMovePct":4.61,"expectedMovePct":9.05,"rrRatio":0.51,"extrinsicRatio":1,"earningsInWindow":false,"contractQuality":{"spread":{"cls":"good","label":"Tight"},"oi":{"cls":"good","label":"Liquid"},"delta":{"cls":"good","label":"Balanced"},"theta":{"cls":"fair","label":"Normal"},"iv":{"cls":"bad","label":"Elevated"},"overall":"fair"},"qualityScore":0.883}},{"symbol":"KWEB","side":"put","score":-3,"conviction":3,"compositeScore":2.553,"thesis":"Bearish setup on KWEB: 7-day red run (-12.6%); MACD below signal (bearish); IV elevated (97th %ile) — expensive premium.","drivers":[{"tag":"streak","weight":-3,"text":"7-day red run (-12.6%)"},{"tag":"macd","weight":-1,"text":"MACD below signal (bearish)"},{"tag":"iv","weight":1,"text":"IV elevated (97th %ile) — expensive premium"}],"spot":26.91,"sector":null,"sentiment":null,"fundamentalsVerdict":null,"rsi":35.44,"ivPctile":97,"streak":{"color":"red","days":7,"cumulativePct":-12.591985058154252},"contract":{"strike":27,"expiry":1784246400,"expiryLabel":"Jul 16 '26","dte":53,"bid":1.13,"ask":1.3,"mid":1.21,"last":1.26,"iv":0.3037,"oi":3017,"volume":316,"delta":-0.466,"thetaDay":-0.01,"breakeven":25.79,"breakevenMovePct":4.18,"expectedMovePct":11.56,"rrRatio":0.36,"extrinsicRatio":0.93,"earningsInWindow":false,"contractQuality":{"spread":{"cls":"fair","label":"OK"},"oi":{"cls":"good","label":"Liquid"},"delta":{"cls":"good","label":"Balanced"},"theta":{"cls":"good","label":"Slow"},"iv":{"cls":"bad","label":"Elevated"},"overall":"fair"},"qualityScore":0.851}},{"symbol":"CRWD","side":"call","score":3,"conviction":3,"compositeScore":2.358,"thesis":"Bullish setup on CRWD: 12-day green run (+35.7%); RSI 87 (overbought); MACD above signal (bullish).","drivers":[{"tag":"streak","weight":3,"text":"12-day green run (+35.7%)"},{"tag":"rsi","weight":-1,"text":"RSI 87 (overbought)"},{"tag":"macd","weight":1,"text":"MACD above signal (bullish)"}],"spot":663.46,"sector":"Technology","sentiment":null,"fundamentalsVerdict":null,"rsi":86.86,"ivPctile":38,"streak":{"color":"green","days":12,"cumulativePct":35.69693060439244},"contract":{"strike":700,"expiry":1784246400,"expiryLabel":"Jul 16 '26","dte":53,"bid":39.4,"ask":44,"mid":41.7,"last":42.2,"iv":0.5571,"oi":474,"volume":133,"delta":0.454,"thetaDay":-0.5591,"breakeven":741.7,"breakevenMovePct":11.79,"expectedMovePct":21.2,"rrRatio":0.56,"extrinsicRatio":1,"earningsInWindow":true,"contractQuality":{"spread":{"cls":"fair","label":"OK"},"oi":{"cls":"fair","label":"Light"},"delta":{"cls":"good","label":"Balanced"},"theta":{"cls":"fair","label":"Normal"},"iv":{"cls":"fair","label":"Normal"},"overall":"fair"},"qualityScore":0.786}}]}