{"builtAtIso":"2026-05-28T16:04:58.368Z","minConviction":9,"picks":[{"symbol":"META","side":"call","total":19,"score":19,"conviction":19,"compositeScore":16.834,"recommendation":{"tier":"strong-call","label":"Strong Call","side":"call","conviction":"Very High","sizing":"Full size"},"pillars":{"fundamentals":{"score":9,"signals":[{"key":"earningsSurprise","label":"Earnings Surprise","score":3,"value":"+56.8%","note":"2026-03-31 — actual 10.44 vs est 6.65872","available":true},{"key":"epsGrowth","label":"EPS Growth YoY","score":1,"value":"+62.4%","note":"","available":true},{"key":"revGrowth","label":"Revenue Growth YoY","score":1,"value":"+33.1%","note":"","available":true},{"key":"analystTarget","label":"Analyst Price Target","score":1,"value":"+31% to $826.60","note":"58 analysts","available":true},{"key":"peVsSector","label":"P/E vs Sector","score":1,"value":"23.0","note":"77% of sector median — discount","available":true},{"key":"guidance","label":"Guidance","score":2,"value":"+8.5%","note":"+8.5% FY EPS growth est — in line/raised proxy","available":true},{"key":"majorContract","label":"Major Contract","score":0,"value":null,"note":"no structured contract data — manual check","available":false}]},"technicals":{"score":3,"signals":[{"key":"rsi","label":"RSI 14","score":1,"value":"55.3","note":"rising (+12.7 pts vs 5d ago)","available":true},{"key":"macd","label":"MACD","score":1,"value":"2.54","note":"line above signal — bullish","available":true},{"key":"streak","label":"Streak","score":2,"value":"6d green","note":"+4.9% cumulative","available":true},{"key":"sr","label":"Support/Resistance","score":-1,"value":"±1.7% to R","note":"at 20d resistance $643.00","available":true},{"key":"fiftyTwoWeek","label":"52-Week High/Low","score":0,"value":"41% of range","note":"range $520.26–$796.25","available":true},{"key":"volConf","label":"Volume Confirmation","score":0,"value":"0.48x","note":"no S/R breakout to confirm","available":true}]},"mechanicals":{"score":1,"signals":[{"key":"unusualFlow","label":"Unusual Flow","score":0,"value":null,"note":"no unusual flow today","available":false},{"key":"oi","label":"Open Interest (C/P)","score":1,"value":"2.13x C/P","note":"188,389 calls vs 88,615 puts","available":true},{"key":"shortInterest","label":"Short Interest %","score":-1,"value":"1.5%","note":"1.5% short — complacent / shorts already covered","available":true},{"key":"unusualVolume","label":"Unusual Volume","score":0,"value":"0.48x","note":"0.48x vs 20D avg","available":true},{"key":"spyFlows","label":"SPY flows","score":1,"value":"+0.47%","note":"SPY +0.47% — risk-on tape","available":true}]},"narrative":{"score":6,"signals":[{"key":"positiveCatalyst","label":"Positive Catalyst","score":3,"value":"bullish","note":"news sentiment bullish","available":true},{"key":"sectorNarrative","label":"Sector Narrative","score":2,"value":"tailwind","note":"rides \"Internet Content & Information Watchlist\" (str 80)","available":true},{"key":"socialSentiment","label":"Social Sentiment","score":0,"value":"+27% net","note":"+27% net (624 msgs/24h)","available":true},{"key":"media","label":"Media Coverage","score":1,"value":"5 headlines","note":"5 headlines with bullish tilt","available":true},{"key":"negativeCatalyst","label":"Negative Catalyst","score":0,"value":null,"note":"no negative catalyst flagged","available":true},{"key":"macro","label":"Macro Tail/Headwinds","score":0,"value":null,"note":"no active macro narrative","available":true}]}},"thesis":"Bullish setup on META: Earnings Surprise (+56.8%) — 2026-03-31 — actual 10.44 vs est 6.65872; Positive Catalyst (bullish) — news sentiment bullish; Guidance (+8.5%) — +8.5% FY EPS growth est — in line/raised proxy; Streak (6d green) — +4.9% cumulative; Sector Narrative (tailwind) — rides \"Internet Content & Information Watchlist\" (str 80); EPS Growth YoY (+62.4%); Revenue Growth YoY (+33.1%); Analyst Price Target (+31% to $826.60) — 58 analysts.","drivers":[{"tag":"fundamentals","weight":3,"text":"Earnings Surprise (+56.8%) — 2026-03-31 — actual 10.44 vs est 6.65872"},{"tag":"narrative","weight":3,"text":"Positive Catalyst (bullish) — news sentiment bullish"},{"tag":"fundamentals","weight":2,"text":"Guidance (+8.5%) — +8.5% FY EPS growth est — in line/raised proxy"},{"tag":"technicals","weight":2,"text":"Streak (6d green) — +4.9% cumulative"},{"tag":"narrative","weight":2,"text":"Sector Narrative (tailwind) — rides \"Internet Content & Information Watchlist\" (str 80)"},{"tag":"fundamentals","weight":1,"text":"EPS Growth YoY (+62.4%)"},{"tag":"fundamentals","weight":1,"text":"Revenue Growth YoY (+33.1%)"},{"tag":"fundamentals","weight":1,"text":"Analyst Price Target (+31% to $826.60) — 58 analysts"}],"spot":632.24,"sector":"Communication Services","sentiment":"bullish","fundamentalsVerdict":"strong","rsi":55.31,"ivPctile":33,"streak":{"color":"green","days":6,"cumulativePct":4.8647585251533965},"peers":[{"symbol":"RDDT","total":19,"side":"call","tier":"strong-call","label":"Strong Call"},{"symbol":"APP","total":15,"side":"call","tier":"strong-call","label":"Strong Call"},{"symbol":"SPOT","total":14,"side":"call","tier":"call","label":"Call"},{"symbol":"GOOGL","total":13,"side":"call","tier":"call","label":"Call"},{"symbol":"NFLX","total":7,"side":null,"tier":"no-trade","label":"No Trade"}],"contract":{"strike":690,"expiry":1784246400,"expiryLabel":"Jul 16 '26","dte":49,"bid":12.7,"ask":13.45,"mid":13.07,"last":12.94,"iv":0.3555,"oi":4309,"volume":360,"delta":0.289,"thetaDay":-0.307,"breakeven":703.08,"breakevenMovePct":11.2,"expectedMovePct":13.07,"rrRatio":0.86,"extrinsicRatio":1,"earningsInWindow":false,"otmPct":9.14,"contractQuality":{"spread":{"cls":"good","label":"Tight"},"oi":{"cls":"good","label":"Liquid"},"delta":{"cls":"fair","label":"OTM"},"theta":{"cls":"fair","label":"Normal"},"iv":{"cls":"good","label":"Calm"},"overall":"fair"},"qualityScore":0.886},"analysis":"META scores +19 — a Strong Call recommendation. The bullish read is led by Fundamentals (+9), reinforced by Narrative (+6). The biggest contributors are Earnings Surprise (+3, +56.8%), Positive Catalyst (+3, bullish), Guidance (+2, +8.5%). Cutting the other way: Support/Resistance (-1, ±1.7% to R), Short Interest % (-1, 1.5%). Within Communication Services we gave META a +19 and APP a +15 — same direction, lower conviction — which is why we'd take META calls over APP calls. The suggested calls sit ~9.1% OTM with 49d to expiry, delta 0.29, mid $13.07 — well inside the 5-25% OTM / Δ 0.15-0.40 / ≤$35 premium criteria."},{"symbol":"RDDT","side":"call","total":19,"score":19,"conviction":19,"compositeScore":15.656,"recommendation":{"tier":"strong-call","label":"Strong Call","side":"call","conviction":"Very High","sizing":"Full size"},"pillars":{"fundamentals":{"score":9,"signals":[{"key":"earningsSurprise","label":"Earnings Surprise","score":3,"value":"+79.1%","note":"2026-03-31 — actual 1.01 vs est 0.56388","available":true},{"key":"epsGrowth","label":"EPS Growth YoY","score":1,"value":"+675.0%","note":"","available":true},{"key":"revGrowth","label":"Revenue Growth YoY","score":1,"value":"+69.1%","note":"","available":true},{"key":"analystTarget","label":"Analyst Price Target","score":1,"value":"+41% to $224.92","note":"31 analysts","available":true},{"key":"peVsSector","label":"P/E vs Sector","score":0,"value":"45.6","note":"153% of sector median (45.6 vs 29.8)","available":true},{"key":"guidance","label":"Guidance","score":3,"value":"+54.7%","note":"+54.7% FY EPS growth est — raised proxy","available":true},{"key":"majorContract","label":"Major Contract","score":0,"value":null,"note":"no structured contract data — manual check","available":false}]},"technicals":{"score":2,"signals":[{"key":"rsi","label":"RSI 14","score":1,"value":"54.3","note":"rising (+11.3 pts vs 5d ago)","available":true},{"key":"macd","label":"MACD","score":-1,"value":"-0.69","note":"line below signal — bearish","available":true},{"key":"streak","label":"Streak","score":2,"value":"3d green","note":"+12.1% cumulative","available":true},{"key":"sr","label":"Support/Resistance","score":0,"value":null,"note":"between S/R levels","available":true},{"key":"fiftyTwoWeek","label":"52-Week High/Low","score":0,"value":"30% of range","note":"range $106.34–$282.95","available":true},{"key":"volConf","label":"Volume Confirmation","score":0,"value":"0.38x","note":"no S/R breakout to confirm","available":true}]},"mechanicals":{"score":1,"signals":[{"key":"unusualFlow","label":"Unusual Flow","score":0,"value":null,"note":"no unusual flow today","available":false},{"key":"oi","label":"Open Interest (C/P)","score":0,"value":"1.23x C/P","note":"65,070 calls vs 52,832 puts","available":true},{"key":"shortInterest","label":"Short Interest %","score":0,"value":"9.4%","note":"9.4% of float short — neutral band","available":true},{"key":"unusualVolume","label":"Unusual Volume","score":0,"value":"0.38x","note":"0.38x vs 20D avg","available":true},{"key":"spyFlows","label":"SPY flows","score":1,"value":"+0.47%","note":"SPY +0.47% — risk-on tape","available":true}]},"narrative":{"score":7,"signals":[{"key":"positiveCatalyst","label":"Positive Catalyst","score":3,"value":"bullish","note":"news sentiment bullish","available":true},{"key":"sectorNarrative","label":"Sector Narrative","score":2,"value":"tailwind","note":"rides \"Internet Content & Information Watchlist\" (str 80)","available":true},{"key":"socialSentiment","label":"Social Sentiment","score":1,"value":"+65% net","note":"+65% net (344.6409989594173 msgs/24h)","available":true},{"key":"media","label":"Media Coverage","score":1,"value":"5 headlines","note":"5 headlines with bullish tilt","available":true},{"key":"negativeCatalyst","label":"Negative Catalyst","score":0,"value":null,"note":"no negative catalyst flagged","available":true},{"key":"macro","label":"Macro Tail/Headwinds","score":0,"value":null,"note":"no active macro narrative","available":true}]}},"thesis":"Bullish setup on RDDT: Earnings Surprise (+79.1%) — 2026-03-31 — actual 1.01 vs est 0.56388; Guidance (+54.7%) — +54.7% FY EPS growth est — raised proxy; Positive Catalyst (bullish) — news sentiment bullish; Streak (3d green) — +12.1% cumulative; Sector Narrative (tailwind) — rides \"Internet Content & Information Watchlist\" (str 80); EPS Growth YoY (+675.0%); Revenue Growth YoY (+69.1%); Analyst Price Target (+41% to $224.92) — 31 analysts.","drivers":[{"tag":"fundamentals","weight":3,"text":"Earnings Surprise (+79.1%) — 2026-03-31 — actual 1.01 vs est 0.56388"},{"tag":"fundamentals","weight":3,"text":"Guidance (+54.7%) — +54.7% FY EPS growth est — raised proxy"},{"tag":"narrative","weight":3,"text":"Positive Catalyst (bullish) — news sentiment bullish"},{"tag":"technicals","weight":2,"text":"Streak (3d green) — +12.1% cumulative"},{"tag":"narrative","weight":2,"text":"Sector Narrative (tailwind) — rides \"Internet Content & Information Watchlist\" (str 80)"},{"tag":"fundamentals","weight":1,"text":"EPS Growth YoY (+675.0%)"},{"tag":"fundamentals","weight":1,"text":"Revenue Growth YoY (+69.1%)"},{"tag":"fundamentals","weight":1,"text":"Analyst Price Target (+41% to $224.92) — 31 analysts"}],"spot":159.435,"sector":"Communication Services","sentiment":"bullish","fundamentalsVerdict":"strong","rsi":54.33,"ivPctile":72,"streak":{"color":"green","days":3,"cumulativePct":12.100667942339747},"peers":[{"symbol":"META","total":19,"side":"call","tier":"strong-call","label":"Strong Call"},{"symbol":"APP","total":15,"side":"call","tier":"strong-call","label":"Strong Call"},{"symbol":"SPOT","total":14,"side":"call","tier":"call","label":"Call"},{"symbol":"GOOGL","total":13,"side":"call","tier":"call","label":"Call"},{"symbol":"NFLX","total":7,"side":null,"tier":"no-trade","label":"No Trade"}],"contract":{"strike":190,"expiry":1784246400,"expiryLabel":"Jul 16 '26","dte":49,"bid":6.7,"ask":7.15,"mid":6.93,"last":7,"iv":0.7057,"oi":656,"volume":167,"delta":0.3,"thetaDay":-0.151,"breakeven":196.93,"breakevenMovePct":23.51,"expectedMovePct":25.94,"rrRatio":0.91,"extrinsicRatio":1,"earningsInWindow":false,"otmPct":19.17,"contractQuality":{"spread":{"cls":"good","label":"Tight"},"oi":{"cls":"good","label":"Liquid"},"delta":{"cls":"fair","label":"Skewed"},"theta":{"cls":"fair","label":"Normal"},"iv":{"cls":"bad","label":"Elevated"},"overall":"fair"},"qualityScore":0.824},"analysis":"RDDT scores +19 — a Strong Call recommendation. The bullish read is led by Fundamentals (+9), reinforced by Narrative (+7). The biggest contributors are Earnings Surprise (+3, +79.1%), Guidance (+3, +54.7%), Positive Catalyst (+3, bullish). Cutting the other way: MACD (-1, -0.69). Within Communication Services we gave RDDT a +19 and APP a +15 — same direction, lower conviction — which is why we'd take RDDT calls over APP calls. The suggested calls sit ~19.2% OTM with 49d to expiry, delta 0.30, mid $6.93 — well inside the 5-25% OTM / Δ 0.15-0.40 / ≤$35 premium criteria."},{"symbol":"SMCI","side":"call","total":19,"score":19,"conviction":19,"compositeScore":14.212,"recommendation":{"tier":"strong-call","label":"Strong Call","side":"call","conviction":"Very High","sizing":"Full size"},"pillars":{"fundamentals":{"score":8,"signals":[{"key":"earningsSurprise","label":"Earnings Surprise","score":3,"value":"+34.5%","note":"2026-03-31 — actual 0.84 vs est 0.62451","available":true},{"key":"epsGrowth","label":"EPS Growth YoY","score":1,"value":"+326.0%","note":"","available":true},{"key":"revGrowth","label":"Revenue Growth YoY","score":1,"value":"+122.7%","note":"","available":true},{"key":"analystTarget","label":"Analyst Price Target","score":-1,"value":"-13% to $37.13","note":"16 analysts","available":true},{"key":"peVsSector","label":"P/E vs Sector","score":1,"value":"22.4","note":"42% of sector median — discount","available":true},{"key":"guidance","label":"Guidance","score":3,"value":"+26.0%","note":"+26.0% FY EPS growth est — raised proxy","available":true},{"key":"majorContract","label":"Major Contract","score":0,"value":null,"note":"no structured contract data — manual check","available":false}]},"technicals":{"score":1,"signals":[{"key":"rsi","label":"RSI 14","score":-1,"value":"75.8","note":"overbought","available":true},{"key":"macd","label":"MACD","score":1,"value":"0.82","note":"line above signal — bullish","available":true},{"key":"streak","label":"Streak","score":2,"value":"6d green","note":"+34.5% cumulative","available":true},{"key":"sr","label":"Support/Resistance","score":-1,"value":"±2.2% to R","note":"at 20d resistance $43.54","available":true},{"key":"fiftyTwoWeek","label":"52-Week High/Low","score":0,"value":"54% of range","note":"range $19.48–$62.36","available":true},{"key":"volConf","label":"Volume Confirmation","score":0,"value":"1.06x","note":"no S/R breakout to confirm","available":true}]},"mechanicals":{"score":3,"signals":[{"key":"unusualFlow","label":"Unusual Flow","score":0,"value":null,"note":"no unusual flow today","available":false},{"key":"oi","label":"Open Interest (C/P)","score":1,"value":"2.59x C/P","note":"442,063 calls vs 170,880 puts","available":true},{"key":"shortInterest","label":"Short Interest %","score":1,"value":"18.0%","note":"18.0% short + stock +11.47% today — squeeze setup","available":true},{"key":"unusualVolume","label":"Unusual Volume","score":0,"value":"1.06x","note":"1.06x vs 20D avg","available":true},{"key":"spyFlows","label":"SPY flows","score":1,"value":"+0.47%","note":"SPY +0.47% — risk-on tape","available":true}]},"narrative":{"score":7,"signals":[{"key":"positiveCatalyst","label":"Positive Catalyst","score":3,"value":"bullish","note":"news sentiment bullish","available":true},{"key":"sectorNarrative","label":"Sector Narrative","score":2,"value":"tailwind","note":"rides \"AI Infrastructure Buildout\" (str 95)","available":true},{"key":"socialSentiment","label":"Social Sentiment","score":1,"value":"+41% net","note":"+41% net (696 msgs/24h)","available":true},{"key":"media","label":"Media Coverage","score":1,"value":"5 headlines","note":"5 headlines with bullish tilt","available":true},{"key":"negativeCatalyst","label":"Negative Catalyst","score":0,"value":null,"note":"no negative catalyst flagged","available":true},{"key":"macro","label":"Macro Tail/Headwinds","score":0,"value":null,"note":"no active macro narrative","available":true}]}},"thesis":"Bullish setup on SMCI: Earnings Surprise (+34.5%) — 2026-03-31 — actual 0.84 vs est 0.62451; Guidance (+26.0%) — +26.0% FY EPS growth est — raised proxy; Positive Catalyst (bullish) — news sentiment bullish; Streak (6d green) — +34.5% cumulative; Sector Narrative (tailwind) — rides \"AI Infrastructure Buildout\" (str 95); EPS Growth YoY (+326.0%); Revenue Growth YoY (+122.7%); Analyst Price Target (-13% to $37.13) — 16 analysts.","drivers":[{"tag":"fundamentals","weight":3,"text":"Earnings Surprise (+34.5%) — 2026-03-31 — actual 0.84 vs est 0.62451"},{"tag":"fundamentals","weight":3,"text":"Guidance (+26.0%) — +26.0% FY EPS growth est — raised proxy"},{"tag":"narrative","weight":3,"text":"Positive Catalyst (bullish) — news sentiment bullish"},{"tag":"technicals","weight":2,"text":"Streak (6d green) — +34.5% cumulative"},{"tag":"narrative","weight":2,"text":"Sector Narrative (tailwind) — rides \"AI Infrastructure Buildout\" (str 95)"},{"tag":"fundamentals","weight":1,"text":"EPS Growth YoY (+326.0%)"},{"tag":"fundamentals","weight":1,"text":"Revenue Growth YoY (+122.7%)"},{"tag":"fundamentals","weight":-1,"text":"Analyst Price Target (-13% to $37.13) — 16 analysts"}],"spot":42.59,"sector":"Technology","sentiment":"bullish","fundamentalsVerdict":"mixed","rsi":75.76,"ivPctile":75,"streak":{"color":"green","days":6,"cumulativePct":34.504492955032994},"peers":[{"symbol":"ORCL","total":17,"side":"call","tier":"strong-call","label":"Strong Call"},{"symbol":"LRCX","total":17,"side":"call","tier":"strong-call","label":"Strong Call"},{"symbol":"TSM","total":16,"side":"call","tier":"strong-call","label":"Strong Call"},{"symbol":"ACN","total":16,"side":"call","tier":"strong-call","label":"Strong Call"},{"symbol":"STX","total":16,"side":"call","tier":"strong-call","label":"Strong Call"}],"contract":{"strike":50,"expiry":1782432000,"expiryLabel":"Jun 25 '26","dte":28,"bid":2.01,"ask":2.22,"mid":2.12,"last":2.19,"iv":0.9438,"oi":950,"volume":463,"delta":0.321,"thetaDay":-0.0722,"breakeven":52.12,"breakevenMovePct":22.36,"expectedMovePct":26.3,"rrRatio":0.85,"extrinsicRatio":1,"earningsInWindow":false,"otmPct":17.4,"contractQuality":{"spread":{"cls":"fair","label":"OK"},"oi":{"cls":"good","label":"Liquid"},"delta":{"cls":"fair","label":"Skewed"},"theta":{"cls":"bad","label":"Bleeding"},"iv":{"cls":"bad","label":"Elevated"},"overall":"bad"},"qualityScore":0.748},"analysis":"SMCI scores +19 — a Strong Call recommendation. The bullish read is led by Fundamentals (+8), reinforced by Narrative (+7). The biggest contributors are Earnings Surprise (+3, +34.5%), Guidance (+3, +26.0%), Positive Catalyst (+3, bullish). Cutting the other way: Analyst Price Target (-1, -13% to $37.13), RSI 14 (-1, 75.8). Within Technology we gave SMCI a +19 and ORCL a +17 — same direction, lower conviction — which is why we'd take SMCI calls over ORCL calls. The suggested calls sit ~17.4% OTM with 28d to expiry, delta 0.32, mid $2.12 — well inside the 5-25% OTM / Δ 0.15-0.40 / ≤$35 premium criteria."},{"symbol":"ORCL","side":"call","total":17,"score":17,"conviction":17,"compositeScore":13.821,"recommendation":{"tier":"strong-call","label":"Strong Call","side":"call","conviction":"Very High","sizing":"Full size"},"pillars":{"fundamentals":{"score":9,"signals":[{"key":"earningsSurprise","label":"Earnings Surprise","score":2,"value":"+5.7%","note":"2026-02-28 — actual 1.79 vs est 1.69362","available":true},{"key":"epsGrowth","label":"EPS Growth YoY","score":1,"value":"+24.5%","note":"","available":true},{"key":"revGrowth","label":"Revenue Growth YoY","score":1,"value":"+21.7%","note":"","available":true},{"key":"analystTarget","label":"Analyst Price Target","score":1,"value":"+20% to $244.03","note":"39 analysts","available":true},{"key":"peVsSector","label":"P/E vs Sector","score":1,"value":"36.3","note":"68% of sector median — discount","available":true},{"key":"guidance","label":"Guidance","score":3,"value":"+23.6%","note":"+23.6% FY EPS growth est — raised proxy","available":true},{"key":"majorContract","label":"Major Contract","score":0,"value":null,"note":"no structured contract data — manual check","available":false}]},"technicals":{"score":1,"signals":[{"key":"rsi","label":"RSI 14","score":1,"value":"65.5","note":"rising (+8.7 pts vs 5d ago)","available":true},{"key":"macd","label":"MACD","score":-1,"value":"-0.15","note":"line below signal — bearish","available":true},{"key":"streak","label":"Streak","score":2,"value":"6d green","note":"+11.3% cumulative","available":true},{"key":"sr","label":"Support/Resistance","score":-1,"value":"±0.8% to R","note":"at 20d resistance $204.31","available":true},{"key":"fiftyTwoWeek","label":"52-Week High/Low","score":0,"value":"32% of range","note":"range $134.57–$345.72","available":true},{"key":"volConf","label":"Volume Confirmation","score":0,"value":"0.68x","note":"no S/R breakout to confirm","available":true}]},"mechanicals":{"score":0,"signals":[{"key":"unusualFlow","label":"Unusual Flow","score":0,"value":null,"note":"no unusual flow today","available":false},{"key":"oi","label":"Open Interest (C/P)","score":0,"value":"1.43x C/P","note":"414,624 calls vs 290,678 puts","available":true},{"key":"shortInterest","label":"Short Interest %","score":-1,"value":"2.1%","note":"2.1% short — complacent / shorts already covered","available":true},{"key":"unusualVolume","label":"Unusual Volume","score":0,"value":"0.68x","note":"0.68x vs 20D avg","available":true},{"key":"spyFlows","label":"SPY flows","score":1,"value":"+0.47%","note":"SPY +0.47% — risk-on tape","available":true}]},"narrative":{"score":7,"signals":[{"key":"positiveCatalyst","label":"Positive Catalyst","score":3,"value":"bullish","note":"news sentiment bullish","available":true},{"key":"sectorNarrative","label":"Sector Narrative","score":2,"value":"tailwind","note":"rides \"AI Infrastructure Buildout\" (str 95)","available":true},{"key":"socialSentiment","label":"Social Sentiment","score":1,"value":"+59% net","note":"+59% net (648 msgs/24h)","available":true},{"key":"media","label":"Media Coverage","score":1,"value":"5 headlines","note":"5 headlines with bullish tilt","available":true},{"key":"negativeCatalyst","label":"Negative Catalyst","score":0,"value":null,"note":"no negative catalyst flagged","available":true},{"key":"macro","label":"Macro Tail/Headwinds","score":0,"value":null,"note":"no active macro narrative","available":true}]}},"thesis":"Bullish setup on ORCL: Guidance (+23.6%) — +23.6% FY EPS growth est — raised proxy; Positive Catalyst (bullish) — news sentiment bullish; Earnings Surprise (+5.7%) — 2026-02-28 — actual 1.79 vs est 1.69362; Streak (6d green) — +11.3% cumulative; Sector Narrative (tailwind) — rides \"AI Infrastructure Buildout\" (str 95); EPS Growth YoY (+24.5%); Revenue Growth YoY (+21.7%); Analyst Price Target (+20% to $244.03) — 39 analysts.","drivers":[{"tag":"fundamentals","weight":3,"text":"Guidance (+23.6%) — +23.6% FY EPS growth est — raised proxy"},{"tag":"narrative","weight":3,"text":"Positive Catalyst (bullish) — news sentiment bullish"},{"tag":"fundamentals","weight":2,"text":"Earnings Surprise (+5.7%) — 2026-02-28 — actual 1.79 vs est 1.69362"},{"tag":"technicals","weight":2,"text":"Streak (6d green) — +11.3% cumulative"},{"tag":"narrative","weight":2,"text":"Sector Narrative (tailwind) — rides \"AI Infrastructure Buildout\" (str 95)"},{"tag":"fundamentals","weight":1,"text":"EPS Growth YoY (+24.5%)"},{"tag":"fundamentals","weight":1,"text":"Revenue Growth YoY (+21.7%)"},{"tag":"fundamentals","weight":1,"text":"Analyst Price Target (+20% to $244.03) — 39 analysts"}],"spot":202.6,"sector":"Technology","sentiment":"bullish","fundamentalsVerdict":"mixed","rsi":65.52,"ivPctile":25,"streak":{"color":"green","days":6,"cumulativePct":11.325053966593618},"peers":[{"symbol":"SMCI","total":19,"side":"call","tier":"strong-call","label":"Strong Call"},{"symbol":"LRCX","total":17,"side":"call","tier":"strong-call","label":"Strong Call"},{"symbol":"TSM","total":16,"side":"call","tier":"strong-call","label":"Strong Call"},{"symbol":"ACN","total":16,"side":"call","tier":"strong-call","label":"Strong Call"},{"symbol":"STX","total":16,"side":"call","tier":"strong-call","label":"Strong Call"}],"contract":{"strike":240,"expiry":1784246400,"expiryLabel":"Jul 16 '26","dte":49,"bid":8.4,"ask":8.75,"mid":8.57,"last":8.75,"iv":0.6845,"oi":8297,"volume":2532,"delta":0.3,"thetaDay":-0.1862,"breakeven":248.57,"breakevenMovePct":22.69,"expectedMovePct":25.16,"rrRatio":0.9,"extrinsicRatio":1,"earningsInWindow":true,"otmPct":18.46,"contractQuality":{"spread":{"cls":"good","label":"Tight"},"oi":{"cls":"good","label":"Liquid"},"delta":{"cls":"fair","label":"Skewed"},"theta":{"cls":"fair","label":"Normal"},"iv":{"cls":"good","label":"Calm"},"overall":"fair"},"qualityScore":0.813},"analysis":"ORCL scores +17 — a Strong Call recommendation. The bullish read is led by Fundamentals (+9), reinforced by Narrative (+7). The biggest contributors are Guidance (+3, +23.6%), Positive Catalyst (+3, bullish), Earnings Surprise (+2, +5.7%). Cutting the other way: MACD (-1, -0.15), Support/Resistance (-1, ±0.8% to R). Within Technology we gave ORCL a +17 and TSM a +16 — same direction, lower conviction — which is why we'd take ORCL calls over TSM calls. The suggested calls sit ~18.5% OTM with 49d to expiry, delta 0.30, mid $8.57 — well inside the 5-25% OTM / Δ 0.15-0.40 / ≤$35 premium criteria."},{"symbol":"MSFT","side":"call","total":15,"score":15,"conviction":15,"compositeScore":13.815,"recommendation":{"tier":"strong-call","label":"Strong Call","side":"call","conviction":"Very High","sizing":"Full size"},"pillars":{"fundamentals":{"score":9,"signals":[{"key":"earningsSurprise","label":"Earnings Surprise","score":2,"value":"+5.2%","note":"2026-03-31 — actual 4.27 vs est 4.05827","available":true},{"key":"epsGrowth","label":"EPS Growth YoY","score":1,"value":"+23.4%","note":"","available":true},{"key":"revGrowth","label":"Revenue Growth YoY","score":1,"value":"+18.3%","note":"","available":true},{"key":"analystTarget","label":"Analyst Price Target","score":1,"value":"+32% to $560.63","note":"54 analysts","available":true},{"key":"peVsSector","label":"P/E vs Sector","score":1,"value":"25.3","note":"47% of sector median — discount","available":true},{"key":"guidance","label":"Guidance","score":3,"value":"+23.3%","note":"+23.3% FY EPS growth est — raised proxy","available":true},{"key":"majorContract","label":"Major Contract","score":0,"value":null,"note":"no structured contract data — manual check","available":false}]},"technicals":{"score":-2,"signals":[{"key":"rsi","label":"RSI 14","score":0,"value":"58.0","note":"neutral range, flat momentum","available":true},{"key":"macd","label":"MACD","score":-1,"value":"-0.37","note":"line below signal — bearish","available":true},{"key":"streak","label":"Streak","score":0,"value":"1d green","note":"+2.9% cumulative","available":true},{"key":"sr","label":"Support/Resistance","score":-1,"value":"±1.9% to R","note":"at 20d resistance $432.70","available":true},{"key":"fiftyTwoWeek","label":"52-Week High/Low","score":0,"value":"34% of range","note":"range $356.28–$555.45","available":true},{"key":"volConf","label":"Volume Confirmation","score":0,"value":"0.61x","note":"no S/R breakout to confirm","available":true}]},"mechanicals":{"score":1,"signals":[{"key":"unusualFlow","label":"Unusual Flow","score":0,"value":null,"note":"no unusual flow today","available":false},{"key":"oi","label":"Open Interest (C/P)","score":1,"value":"2.40x C/P","note":"237,584 calls vs 99,172 puts","available":true},{"key":"shortInterest","label":"Short Interest %","score":-1,"value":"1.0%","note":"1.0% short — complacent / shorts already covered","available":true},{"key":"unusualVolume","label":"Unusual Volume","score":0,"value":"0.61x","note":"0.61x vs 20D avg","available":true},{"key":"spyFlows","label":"SPY flows","score":1,"value":"+0.47%","note":"SPY +0.47% — risk-on tape","available":true}]},"narrative":{"score":7,"signals":[{"key":"positiveCatalyst","label":"Positive Catalyst","score":3,"value":"bullish","note":"news sentiment bullish","available":true},{"key":"sectorNarrative","label":"Sector Narrative","score":2,"value":"tailwind","note":"rides \"AI Infrastructure Buildout\" (str 95)","available":true},{"key":"socialSentiment","label":"Social Sentiment","score":1,"value":"+56% net","note":"+56% net (384 msgs/24h)","available":true},{"key":"media","label":"Media Coverage","score":1,"value":"5 headlines","note":"5 headlines with bullish tilt","available":true},{"key":"negativeCatalyst","label":"Negative Catalyst","score":0,"value":null,"note":"no negative catalyst flagged","available":true},{"key":"macro","label":"Macro Tail/Headwinds","score":0,"value":null,"note":"no active macro narrative","available":true}]}},"thesis":"Bullish setup on MSFT: Guidance (+23.3%) — +23.3% FY EPS growth est — raised proxy; Positive Catalyst (bullish) — news sentiment bullish; Earnings Surprise (+5.2%) — 2026-03-31 — actual 4.27 vs est 4.05827; Sector Narrative (tailwind) — rides \"AI Infrastructure Buildout\" (str 95); EPS Growth YoY (+23.4%); Revenue Growth YoY (+18.3%); Analyst Price Target (+32% to $560.63) — 54 analysts; P/E vs Sector (25.3) — 47% of sector median — discount.","drivers":[{"tag":"fundamentals","weight":3,"text":"Guidance (+23.3%) — +23.3% FY EPS growth est — raised proxy"},{"tag":"narrative","weight":3,"text":"Positive Catalyst (bullish) — news sentiment bullish"},{"tag":"fundamentals","weight":2,"text":"Earnings Surprise (+5.2%) — 2026-03-31 — actual 4.27 vs est 4.05827"},{"tag":"narrative","weight":2,"text":"Sector Narrative (tailwind) — rides \"AI Infrastructure Buildout\" (str 95)"},{"tag":"fundamentals","weight":1,"text":"EPS Growth YoY (+23.4%)"},{"tag":"fundamentals","weight":1,"text":"Revenue Growth YoY (+18.3%)"},{"tag":"fundamentals","weight":1,"text":"Analyst Price Target (+32% to $560.63) — 54 analysts"},{"tag":"fundamentals","weight":1,"text":"P/E vs Sector (25.3) — 47% of sector median — discount"}],"spot":424.71,"sector":"Technology","sentiment":"bullish","fundamentalsVerdict":"strong","rsi":58.02,"ivPctile":48,"streak":{"color":"green","days":1,"cumulativePct":2.912736235383573},"peers":[{"symbol":"SMCI","total":19,"side":"call","tier":"strong-call","label":"Strong Call"},{"symbol":"ORCL","total":17,"side":"call","tier":"strong-call","label":"Strong Call"},{"symbol":"LRCX","total":17,"side":"call","tier":"strong-call","label":"Strong Call"},{"symbol":"TSM","total":16,"side":"call","tier":"strong-call","label":"Strong Call"},{"symbol":"ACN","total":16,"side":"call","tier":"strong-call","label":"Strong Call"}],"contract":{"strike":460,"expiry":1784246400,"expiryLabel":"Jul 16 '26","dte":49,"bid":7.6,"ask":7.9,"mid":7.75,"last":7.74,"iv":0.3187,"oi":5682,"volume":996,"delta":0.284,"thetaDay":-0.1848,"breakeven":467.75,"breakevenMovePct":10.13,"expectedMovePct":11.72,"rrRatio":0.87,"extrinsicRatio":1,"earningsInWindow":false,"otmPct":8.31,"contractQuality":{"spread":{"cls":"good","label":"Tight"},"oi":{"cls":"good","label":"Liquid"},"delta":{"cls":"fair","label":"OTM"},"theta":{"cls":"fair","label":"Normal"},"iv":{"cls":"fair","label":"Normal"},"overall":"fair"},"qualityScore":0.921},"analysis":"MSFT scores +15 — a Strong Call recommendation. The bullish read is led by Fundamentals (+9), reinforced by Narrative (+7). The biggest contributors are Guidance (+3, +23.3%), Positive Catalyst (+3, bullish), Earnings Surprise (+2, +5.2%). Cutting the other way: MACD (-1, -0.37), Support/Resistance (-1, ±1.9% to R). Within Technology, the next-closest same-direction peer is SMCI at +19 — well below MSFT's +15, so MSFT is the cleaner calls expression. The suggested calls sit ~8.3% OTM with 49d to expiry, delta 0.28, mid $7.75 — well inside the 5-25% OTM / Δ 0.15-0.40 / ≤$35 premium criteria."},{"symbol":"LRCX","side":"call","total":17,"score":17,"conviction":17,"compositeScore":13.787,"recommendation":{"tier":"strong-call","label":"Strong Call","side":"call","conviction":"Very High","sizing":"Full size"},"pillars":{"fundamentals":{"score":7,"signals":[{"key":"earningsSurprise","label":"Earnings Surprise","score":2,"value":"+7.9%","note":"2026-03-31 — actual 1.47 vs est 1.3628","available":true},{"key":"epsGrowth","label":"EPS Growth YoY","score":1,"value":"+40.8%","note":"","available":true},{"key":"revGrowth","label":"Revenue Growth YoY","score":1,"value":"+23.8%","note":"","available":true},{"key":"analystTarget","label":"Analyst Price Target","score":0,"value":"-3% to $312.13","note":"32 analysts","available":true},{"key":"peVsSector","label":"P/E vs Sector","score":0,"value":"60.7","note":"114% of sector median (60.7 vs 53.4)","available":true},{"key":"guidance","label":"Guidance","score":3,"value":"+37.1%","note":"+37.1% FY EPS growth est — raised proxy","available":true},{"key":"majorContract","label":"Major Contract","score":0,"value":null,"note":"no structured contract data — manual check","available":false}]},"technicals":{"score":3,"signals":[{"key":"rsi","label":"RSI 14","score":1,"value":"67.2","note":"rising (+8.1 pts vs 5d ago)","available":true},{"key":"macd","label":"MACD","score":1,"value":"2.37","note":"line above signal — bullish","available":true},{"key":"streak","label":"Streak","score":2,"value":"6d green","note":"+16.5% cumulative","available":true},{"key":"sr","label":"Support/Resistance","score":0,"value":null,"note":"between S/R levels","available":true},{"key":"fiftyTwoWeek","label":"52-Week High/Low","score":-1,"value":"95% of range","note":"3.9% below 52w high — extended / fade risk","available":true},{"key":"volConf","label":"Volume Confirmation","score":0,"value":"0.34x","note":"no S/R breakout to confirm","available":true}]},"mechanicals":{"score":0,"signals":[{"key":"unusualFlow","label":"Unusual Flow","score":0,"value":null,"note":"no unusual flow today","available":false},{"key":"oi","label":"Open Interest (C/P)","score":0,"value":"1.19x C/P","note":"100,256 calls vs 84,568 puts","available":true},{"key":"shortInterest","label":"Short Interest %","score":-1,"value":"2.9%","note":"2.9% short — complacent / shorts already covered","available":true},{"key":"unusualVolume","label":"Unusual Volume","score":0,"value":"0.34x","note":"0.34x vs 20D avg","available":true},{"key":"spyFlows","label":"SPY flows","score":1,"value":"+0.47%","note":"SPY +0.47% — risk-on tape","available":true}]},"narrative":{"score":7,"signals":[{"key":"positiveCatalyst","label":"Positive Catalyst","score":3,"value":"bullish","note":"news sentiment bullish","available":true},{"key":"sectorNarrative","label":"Sector Narrative","score":2,"value":"tailwind","note":"rides \"Semiconductor Equipment & Materials Buildout\" (str 85)","available":true},{"key":"socialSentiment","label":"Social Sentiment","score":1,"value":"+40% net","note":"+40% net (16.68456137369555 msgs/24h)","available":true},{"key":"media","label":"Media Coverage","score":1,"value":"5 headlines","note":"5 headlines with bullish tilt","available":true},{"key":"negativeCatalyst","label":"Negative Catalyst","score":0,"value":null,"note":"no negative catalyst flagged","available":true},{"key":"macro","label":"Macro Tail/Headwinds","score":0,"value":null,"note":"no active macro narrative","available":true}]}},"thesis":"Bullish setup on LRCX: Guidance (+37.1%) — +37.1% FY EPS growth est — raised proxy; Positive Catalyst (bullish) — news sentiment bullish; Earnings Surprise (+7.9%) — 2026-03-31 — actual 1.47 vs est 1.3628; Streak (6d green) — +16.5% cumulative; Sector Narrative (tailwind) — rides \"Semiconductor Equipment & Materials Buildout\" (str 85); EPS Growth YoY (+40.8%); Revenue Growth YoY (+23.8%); RSI 14 (67.2) — rising (+8.1 pts vs 5d ago).","drivers":[{"tag":"fundamentals","weight":3,"text":"Guidance (+37.1%) — +37.1% FY EPS growth est — raised proxy"},{"tag":"narrative","weight":3,"text":"Positive Catalyst (bullish) — news sentiment bullish"},{"tag":"fundamentals","weight":2,"text":"Earnings Surprise (+7.9%) — 2026-03-31 — actual 1.47 vs est 1.3628"},{"tag":"technicals","weight":2,"text":"Streak (6d green) — +16.5% cumulative"},{"tag":"narrative","weight":2,"text":"Sector Narrative (tailwind) — rides \"Semiconductor Equipment & Materials Buildout\" (str 85)"},{"tag":"fundamentals","weight":1,"text":"EPS Growth YoY (+40.8%)"},{"tag":"fundamentals","weight":1,"text":"Revenue Growth YoY (+23.8%)"},{"tag":"technicals","weight":1,"text":"RSI 14 (67.2) — rising (+8.1 pts vs 5d ago)"}],"spot":320.83,"sector":"Technology","sentiment":"bullish","fundamentalsVerdict":"strong","rsi":67.17,"ivPctile":27,"streak":{"color":"green","days":6,"cumulativePct":16.482030544054947},"peers":[{"symbol":"SMCI","total":19,"side":"call","tier":"strong-call","label":"Strong Call"},{"symbol":"ORCL","total":17,"side":"call","tier":"strong-call","label":"Strong Call"},{"symbol":"TSM","total":16,"side":"call","tier":"strong-call","label":"Strong Call"},{"symbol":"ACN","total":16,"side":"call","tier":"strong-call","label":"Strong Call"},{"symbol":"STX","total":16,"side":"call","tier":"strong-call","label":"Strong Call"}],"contract":{"strike":380,"expiry":1784246400,"expiryLabel":"Jul 16 '26","dte":49,"bid":12.35,"ask":12.9,"mid":12.63,"last":11.45,"iv":0.6619,"oi":369,"volume":2,"delta":0.291,"thetaDay":-0.2815,"breakeven":392.63,"breakevenMovePct":22.38,"expectedMovePct":24.33,"rrRatio":0.92,"extrinsicRatio":1,"earningsInWindow":false,"otmPct":18.44,"contractQuality":{"spread":{"cls":"good","label":"Tight"},"oi":{"cls":"fair","label":"Light"},"delta":{"cls":"fair","label":"OTM"},"theta":{"cls":"fair","label":"Normal"},"iv":{"cls":"good","label":"Calm"},"overall":"fair"},"qualityScore":0.811},"analysis":"LRCX scores +17 — a Strong Call recommendation. The bullish read is led by Fundamentals (+7), reinforced by Narrative (+7). The biggest contributors are Guidance (+3, +37.1%), Positive Catalyst (+3, bullish), Earnings Surprise (+2, +7.9%). Cutting the other way: 52-Week High/Low (-1, 95% of range), Short Interest % (-1, 2.9%). Within Technology we gave LRCX a +17 and TSM a +16 — same direction, lower conviction — which is why we'd take LRCX calls over TSM calls. The suggested calls sit ~18.4% OTM with 49d to expiry, delta 0.29, mid $12.63 — well inside the 5-25% OTM / Δ 0.15-0.40 / ≤$35 premium criteria."},{"symbol":"TSM","side":"call","total":16,"score":16,"conviction":16,"compositeScore":13.136,"recommendation":{"tier":"strong-call","label":"Strong Call","side":"call","conviction":"Very High","sizing":"Full size"},"pillars":{"fundamentals":{"score":8,"signals":[{"key":"earningsSurprise","label":"Earnings Surprise","score":2,"value":"+4.7%","note":"2026-03-31 — actual 3.49 vs est 3.33393","available":true},{"key":"epsGrowth","label":"EPS Growth YoY","score":1,"value":"+58.4%","note":"","available":true},{"key":"revGrowth","label":"Revenue Growth YoY","score":1,"value":"+35.1%","note":"","available":true},{"key":"analystTarget","label":"Analyst Price Target","score":0,"value":"+10% to $467.84","note":"18 analysts","available":true},{"key":"peVsSector","label":"P/E vs Sector","score":1,"value":"36.4","note":"68% of sector median — discount","available":true},{"key":"guidance","label":"Guidance","score":3,"value":"+46.6%","note":"+46.6% FY EPS growth est — raised proxy","available":true},{"key":"majorContract","label":"Major Contract","score":0,"value":null,"note":"no structured contract data — manual check","available":false}]},"technicals":{"score":2,"signals":[{"key":"rsi","label":"RSI 14","score":1,"value":"64.2","note":"rising (+9.6 pts vs 5d ago)","available":true},{"key":"macd","label":"MACD","score":1,"value":"0.48","note":"line above signal — bullish","available":true},{"key":"streak","label":"Streak","score":2,"value":"6d green","note":"+8.4% cumulative","available":true},{"key":"sr","label":"Support/Resistance","score":-1,"value":"±0.9% to R","note":"at 20d resistance $430.55","available":true},{"key":"fiftyTwoWeek","label":"52-Week High/Low","score":-1,"value":"98% of range","note":"0.9% below 52w high — extended / fade risk","available":true},{"key":"volConf","label":"Volume Confirmation","score":0,"value":"0.37x","note":"no S/R breakout to confirm","available":true}]},"mechanicals":{"score":0,"signals":[{"key":"unusualFlow","label":"Unusual Flow","score":0,"value":null,"note":"no unusual flow today","available":false},{"key":"oi","label":"Open Interest (C/P)","score":0,"value":"0.89x C/P","note":"244,405 calls vs 275,760 puts","available":true},{"key":"shortInterest","label":"Short Interest %","score":-1,"value":"0.6%","note":"0.6% short — complacent / shorts already covered","available":true},{"key":"unusualVolume","label":"Unusual Volume","score":0,"value":"0.37x","note":"0.37x vs 20D avg","available":true},{"key":"spyFlows","label":"SPY flows","score":1,"value":"+0.47%","note":"SPY +0.47% — risk-on tape","available":true}]},"narrative":{"score":6,"signals":[{"key":"positiveCatalyst","label":"Positive Catalyst","score":3,"value":"bullish","note":"news sentiment bullish","available":true},{"key":"sectorNarrative","label":"Sector Narrative","score":2,"value":"tailwind","note":"rides \"Semiconductors AI Demand\" (str 90)","available":true},{"key":"socialSentiment","label":"Social Sentiment","score":0,"value":"+27% net","note":"+27% net (13.94038957991082 msgs/24h)","available":true},{"key":"media","label":"Media Coverage","score":1,"value":"5 headlines","note":"5 headlines with bullish tilt","available":true},{"key":"negativeCatalyst","label":"Negative Catalyst","score":0,"value":null,"note":"no negative catalyst flagged","available":true},{"key":"macro","label":"Macro Tail/Headwinds","score":0,"value":null,"note":"no active macro narrative","available":true}]}},"thesis":"Bullish setup on TSM: Guidance (+46.6%) — +46.6% FY EPS growth est — raised proxy; Positive Catalyst (bullish) — news sentiment bullish; Earnings Surprise (+4.7%) — 2026-03-31 — actual 3.49 vs est 3.33393; Streak (6d green) — +8.4% cumulative; Sector Narrative (tailwind) — rides \"Semiconductors AI Demand\" (str 90); EPS Growth YoY (+58.4%); Revenue Growth YoY (+35.1%); P/E vs Sector (36.4) — 68% of sector median — discount.","drivers":[{"tag":"fundamentals","weight":3,"text":"Guidance (+46.6%) — +46.6% FY EPS growth est — raised proxy"},{"tag":"narrative","weight":3,"text":"Positive Catalyst (bullish) — news sentiment bullish"},{"tag":"fundamentals","weight":2,"text":"Earnings Surprise (+4.7%) — 2026-03-31 — actual 3.49 vs est 3.33393"},{"tag":"technicals","weight":2,"text":"Streak (6d green) — +8.4% cumulative"},{"tag":"narrative","weight":2,"text":"Sector Narrative (tailwind) — rides \"Semiconductors AI Demand\" (str 90)"},{"tag":"fundamentals","weight":1,"text":"EPS Growth YoY (+58.4%)"},{"tag":"fundamentals","weight":1,"text":"Revenue Growth YoY (+35.1%)"},{"tag":"fundamentals","weight":1,"text":"P/E vs Sector (36.4) — 68% of sector median — discount"}],"spot":426.51,"sector":"Technology","sentiment":"bullish","fundamentalsVerdict":"strong","rsi":64.15,"ivPctile":60,"streak":{"color":"green","days":6,"cumulativePct":8.382468479049809},"peers":[{"symbol":"SMCI","total":19,"side":"call","tier":"strong-call","label":"Strong Call"},{"symbol":"ORCL","total":17,"side":"call","tier":"strong-call","label":"Strong Call"},{"symbol":"LRCX","total":17,"side":"call","tier":"strong-call","label":"Strong Call"},{"symbol":"ACN","total":16,"side":"call","tier":"strong-call","label":"Strong Call"},{"symbol":"STX","total":16,"side":"call","tier":"strong-call","label":"Strong Call"}],"contract":{"strike":480,"expiry":1784246400,"expiryLabel":"Jul 16 '26","dte":49,"bid":11.75,"ask":12.2,"mid":11.97,"last":12.2,"iv":0.4758,"oi":1499,"volume":93,"delta":0.29,"thetaDay":-0.2727,"breakeven":491.98,"breakevenMovePct":15.35,"expectedMovePct":17.49,"rrRatio":0.88,"extrinsicRatio":1,"earningsInWindow":true,"otmPct":12.54,"contractQuality":{"spread":{"cls":"good","label":"Tight"},"oi":{"cls":"good","label":"Liquid"},"delta":{"cls":"fair","label":"OTM"},"theta":{"cls":"fair","label":"Normal"},"iv":{"cls":"fair","label":"Normal"},"overall":"fair"},"qualityScore":0.821},"analysis":"TSM scores +16 — a Strong Call recommendation. The bullish read is led by Fundamentals (+8), reinforced by Narrative (+6). The biggest contributors are Guidance (+3, +46.6%), Positive Catalyst (+3, bullish), Earnings Surprise (+2, +4.7%). Cutting the other way: Support/Resistance (-1, ±0.9% to R), 52-Week High/Low (-1, 98% of range). Within Technology, the next-closest same-direction peer is SMCI at +19 — well below TSM's +16, so TSM is the cleaner calls expression. The suggested calls sit ~12.5% OTM with 49d to expiry, delta 0.29, mid $11.97 — well inside the 5-25% OTM / Δ 0.15-0.40 / ≤$35 premium criteria."},{"symbol":"GD","side":"call","total":16,"score":16,"conviction":16,"compositeScore":11.424,"recommendation":{"tier":"strong-call","label":"Strong Call","side":"call","conviction":"Very High","sizing":"Full size"},"pillars":{"fundamentals":{"score":7,"signals":[{"key":"earningsSurprise","label":"Earnings Surprise","score":2,"value":"+11.0%","note":"2026-03-31 — actual 4.1 vs est 3.69302","available":true},{"key":"epsGrowth","label":"EPS Growth YoY","score":1,"value":"+12.0%","note":"","available":true},{"key":"revGrowth","label":"Revenue Growth YoY","score":1,"value":"+10.3%","note":"","available":true},{"key":"analystTarget","label":"Analyst Price Target","score":1,"value":"+12% to $392.22","note":"21 analysts","available":true},{"key":"peVsSector","label":"P/E vs Sector","score":0,"value":"22.0","note":"100% of sector median (22.0 vs 22.0)","available":true},{"key":"guidance","label":"Guidance","score":2,"value":"+7.7%","note":"+7.7% FY EPS growth est — in line/raised proxy","available":true},{"key":"majorContract","label":"Major Contract","score":0,"value":null,"note":"no structured contract data — manual check","available":false}]},"technicals":{"score":3,"signals":[{"key":"rsi","label":"RSI 14","score":1,"value":"58.2","note":"rising (+8.9 pts vs 5d ago)","available":true},{"key":"macd","label":"MACD","score":1,"value":"0.65","note":"line above signal — bullish","available":true},{"key":"streak","label":"Streak","score":2,"value":"4d green","note":"+3.0% cumulative","available":true},{"key":"sr","label":"Support/Resistance","score":-1,"value":"±1.3% to R","note":"at 20d resistance $353.57","available":true},{"key":"fiftyTwoWeek","label":"52-Week High/Low","score":0,"value":"80% of range","note":"range $268.10–$369.70","available":true},{"key":"volConf","label":"Volume Confirmation","score":0,"value":"0.30x","note":"no S/R breakout to confirm","available":true}]},"mechanicals":{"score":0,"signals":[{"key":"unusualFlow","label":"Unusual Flow","score":0,"value":null,"note":"no unusual flow today","available":false},{"key":"oi","label":"Open Interest (C/P)","score":0,"value":"1.39x C/P","note":"5,174 calls vs 3,709 puts","available":true},{"key":"shortInterest","label":"Short Interest %","score":-1,"value":"1.1%","note":"1.1% short — complacent / shorts already covered","available":true},{"key":"unusualVolume","label":"Unusual Volume","score":0,"value":"0.30x","note":"0.30x vs 20D avg","available":true},{"key":"spyFlows","label":"SPY flows","score":1,"value":"+0.47%","note":"SPY +0.47% — risk-on tape","available":true}]},"narrative":{"score":6,"signals":[{"key":"positiveCatalyst","label":"Positive Catalyst","score":3,"value":"bullish","note":"news sentiment bullish","available":true},{"key":"sectorNarrative","label":"Sector Narrative","score":2,"value":"tailwind","note":"rides \"Aerospace & Defense Spending\" (str 75)","available":true},{"key":"socialSentiment","label":"Social Sentiment","score":0,"value":null,"note":"insufficient social messages","available":false},{"key":"media","label":"Media Coverage","score":1,"value":"5 headlines","note":"5 headlines with bullish tilt","available":true},{"key":"negativeCatalyst","label":"Negative Catalyst","score":0,"value":null,"note":"no negative catalyst flagged","available":true},{"key":"macro","label":"Macro Tail/Headwinds","score":0,"value":null,"note":"no active macro narrative","available":true}]}},"thesis":"Bullish setup on GD: Positive Catalyst (bullish) — news sentiment bullish; Earnings Surprise (+11.0%) — 2026-03-31 — actual 4.1 vs est 3.69302; Guidance (+7.7%) — +7.7% FY EPS growth est — in line/raised proxy; Streak (4d green) — +3.0% cumulative; Sector Narrative (tailwind) — rides \"Aerospace & Defense Spending\" (str 75); EPS Growth YoY (+12.0%); Revenue Growth YoY (+10.3%); Analyst Price Target (+12% to $392.22) — 21 analysts.","drivers":[{"tag":"narrative","weight":3,"text":"Positive Catalyst (bullish) — news sentiment bullish"},{"tag":"fundamentals","weight":2,"text":"Earnings Surprise (+11.0%) — 2026-03-31 — actual 4.1 vs est 3.69302"},{"tag":"fundamentals","weight":2,"text":"Guidance (+7.7%) — +7.7% FY EPS growth est — in line/raised proxy"},{"tag":"technicals","weight":2,"text":"Streak (4d green) — +3.0% cumulative"},{"tag":"narrative","weight":2,"text":"Sector Narrative (tailwind) — rides \"Aerospace & Defense Spending\" (str 75)"},{"tag":"fundamentals","weight":1,"text":"EPS Growth YoY (+12.0%)"},{"tag":"fundamentals","weight":1,"text":"Revenue Growth YoY (+10.3%)"},{"tag":"fundamentals","weight":1,"text":"Analyst Price Target (+12% to $392.22) — 21 analysts"}],"spot":349.0151,"sector":"Industrials","sentiment":"bullish","fundamentalsVerdict":"strong","rsi":58.19,"ivPctile":84,"streak":{"color":"green","days":4,"cumulativePct":3.025803913088004},"peers":[{"symbol":"RDW","total":18,"side":"call","tier":"strong-call","label":"Strong Call"},{"symbol":"CAT","total":13,"side":"call","tier":"call","label":"Call"},{"symbol":"FDX","total":13,"side":"call","tier":"call","label":"Call"},{"symbol":"DE","total":-8,"side":null,"tier":"no-trade","label":"No Trade"},{"symbol":"LUNR","total":6,"side":null,"tier":"no-trade","label":"No Trade"}],"contract":{"strike":370,"expiry":1784246400,"expiryLabel":"Jul 16 '26","dte":49,"bid":3.6,"ask":4.3,"mid":3.95,"last":3.8,"iv":0.2226,"oi":146,"volume":1,"delta":0.275,"thetaDay":-0.1078,"breakeven":373.95,"breakevenMovePct":7.14,"expectedMovePct":8.18,"rrRatio":0.87,"extrinsicRatio":1,"earningsInWindow":false,"otmPct":6.01,"contractQuality":{"spread":{"cls":"bad","label":"Wide"},"oi":{"cls":"fair","label":"Light"},"delta":{"cls":"fair","label":"OTM"},"theta":{"cls":"fair","label":"Normal"},"iv":{"cls":"bad","label":"Elevated"},"overall":"bad"},"qualityScore":0.714},"analysis":"GD scores +16 — a Strong Call recommendation. The bullish read is led by Fundamentals (+7), reinforced by Narrative (+6). The biggest contributors are Positive Catalyst (+3, bullish), Earnings Surprise (+2, +11.0%), Guidance (+2, +7.7%). Cutting the other way: Support/Resistance (-1, ±1.3% to R), Short Interest % (-1, 1.1%). Within Industrials we gave GD a +16 and CAT a +13 — same direction, lower conviction — which is why we'd take GD calls over CAT calls. The suggested calls sit ~6.0% OTM with 49d to expiry, delta 0.28, mid $3.95 — well inside the 5-25% OTM / Δ 0.15-0.40 / ≤$35 premium criteria."},{"symbol":"ACN","side":"call","total":16,"score":16,"conviction":16,"compositeScore":10.864,"recommendation":{"tier":"strong-call","label":"Strong Call","side":"call","conviction":"Very High","sizing":"Full size"},"pillars":{"fundamentals":{"score":7,"signals":[{"key":"earningsSurprise","label":"Earnings Surprise","score":2,"value":"+3.3%","note":"2026-02-28 — actual 2.93 vs est 2.83739","available":true},{"key":"epsGrowth","label":"EPS Growth YoY","score":0,"value":"+4.0%","note":"","available":true},{"key":"revGrowth","label":"Revenue Growth YoY","score":1,"value":"+8.3%","note":"","available":true},{"key":"analystTarget","label":"Analyst Price Target","score":1,"value":"+39% to $247.55","note":"26 analysts","available":true},{"key":"peVsSector","label":"P/E vs Sector","score":1,"value":"14.7","note":"27% of sector median — discount","available":true},{"key":"guidance","label":"Guidance","score":2,"value":"+7.3%","note":"+7.3% FY EPS growth est — in line/raised proxy","available":true},{"key":"majorContract","label":"Major Contract","score":0,"value":null,"note":"no structured contract data — manual check","available":false}]},"technicals":{"score":1,"signals":[{"key":"rsi","label":"RSI 14","score":0,"value":"49.5","note":"neutral range, flat momentum","available":true},{"key":"macd","label":"MACD","score":1,"value":"1.50","note":"line above signal — bullish","available":true},{"key":"streak","label":"Streak","score":0,"value":"1d green","note":"+1.4% cumulative","available":true},{"key":"sr","label":"Support/Resistance","score":0,"value":null,"note":"between S/R levels","available":true},{"key":"fiftyTwoWeek","label":"52-Week High/Low","score":0,"value":"14% of range","note":"range $155.82–$321.77","available":true},{"key":"volConf","label":"Volume Confirmation","score":0,"value":"0.24x","note":"no S/R breakout to confirm","available":true}]},"mechanicals":{"score":2,"signals":[{"key":"unusualFlow","label":"Unusual Flow","score":0,"value":null,"note":"no unusual flow today","available":false},{"key":"oi","label":"Open Interest (C/P)","score":1,"value":"1.87x C/P","note":"38,508 calls vs 20,607 puts","available":true},{"key":"shortInterest","label":"Short Interest %","score":0,"value":"4.4%","note":"4.4% of float short — neutral band","available":true},{"key":"unusualVolume","label":"Unusual Volume","score":0,"value":"0.24x","note":"0.24x vs 20D avg","available":true},{"key":"spyFlows","label":"SPY flows","score":1,"value":"+0.47%","note":"SPY +0.47% — risk-on tape","available":true}]},"narrative":{"score":6,"signals":[{"key":"positiveCatalyst","label":"Positive Catalyst","score":3,"value":"bullish","note":"news sentiment bullish","available":true},{"key":"sectorNarrative","label":"Sector Narrative","score":2,"value":"tailwind","note":"rides \"AI Software & Cloud Adoption\" (str 70)","available":true},{"key":"socialSentiment","label":"Social Sentiment","score":0,"value":null,"note":"insufficient social messages","available":false},{"key":"media","label":"Media Coverage","score":1,"value":"5 headlines","note":"5 headlines with bullish tilt","available":true},{"key":"negativeCatalyst","label":"Negative Catalyst","score":0,"value":null,"note":"no negative catalyst flagged","available":true},{"key":"macro","label":"Macro Tail/Headwinds","score":0,"value":null,"note":"no active macro narrative","available":true}]}},"thesis":"Bullish setup on ACN: Positive Catalyst (bullish) — news sentiment bullish; Earnings Surprise (+3.3%) — 2026-02-28 — actual 2.93 vs est 2.83739; Guidance (+7.3%) — +7.3% FY EPS growth est — in line/raised proxy; Sector Narrative (tailwind) — rides \"AI Software & Cloud Adoption\" (str 70); Revenue Growth YoY (+8.3%); Analyst Price Target (+39% to $247.55) — 26 analysts; P/E vs Sector (14.7) — 27% of sector median — discount; MACD (1.50) — line above signal — bullish.","drivers":[{"tag":"narrative","weight":3,"text":"Positive Catalyst (bullish) — news sentiment bullish"},{"tag":"fundamentals","weight":2,"text":"Earnings Surprise (+3.3%) — 2026-02-28 — actual 2.93 vs est 2.83739"},{"tag":"fundamentals","weight":2,"text":"Guidance (+7.3%) — +7.3% FY EPS growth est — in line/raised proxy"},{"tag":"narrative","weight":2,"text":"Sector Narrative (tailwind) — rides \"AI Software & Cloud Adoption\" (str 70)"},{"tag":"fundamentals","weight":1,"text":"Revenue Growth YoY (+8.3%)"},{"tag":"fundamentals","weight":1,"text":"Analyst Price Target (+39% to $247.55) — 26 analysts"},{"tag":"fundamentals","weight":1,"text":"P/E vs Sector (14.7) — 27% of sector median — discount"},{"tag":"technicals","weight":1,"text":"MACD (1.50) — line above signal — bullish"}],"spot":178.7,"sector":"Technology","sentiment":"bullish","fundamentalsVerdict":"strong","rsi":49.46,"ivPctile":49,"streak":{"color":"green","days":1,"cumulativePct":1.35518223031133},"peers":[{"symbol":"SMCI","total":19,"side":"call","tier":"strong-call","label":"Strong Call"},{"symbol":"ORCL","total":17,"side":"call","tier":"strong-call","label":"Strong Call"},{"symbol":"LRCX","total":17,"side":"call","tier":"strong-call","label":"Strong Call"},{"symbol":"TSM","total":16,"side":"call","tier":"strong-call","label":"Strong Call"},{"symbol":"STX","total":16,"side":"call","tier":"strong-call","label":"Strong Call"}],"contract":{"strike":200,"expiry":1784246400,"expiryLabel":"Jul 16 '26","dte":49,"bid":5.5,"ask":5.9,"mid":5.7,"last":5.66,"iv":0.4984,"oi":136,"volume":14,"delta":0.312,"thetaDay":-0.1236,"breakeven":205.7,"breakevenMovePct":15.11,"expectedMovePct":18.32,"rrRatio":0.82,"extrinsicRatio":1,"earningsInWindow":true,"otmPct":11.92,"contractQuality":{"spread":{"cls":"good","label":"Tight"},"oi":{"cls":"fair","label":"Light"},"delta":{"cls":"fair","label":"Skewed"},"theta":{"cls":"fair","label":"Normal"},"iv":{"cls":"fair","label":"Normal"},"overall":"fair"},"qualityScore":0.679},"analysis":"ACN scores +16 — a Strong Call recommendation. The bullish read is led by Fundamentals (+7), reinforced by Narrative (+6). The biggest contributors are Positive Catalyst (+3, bullish), Earnings Surprise (+2, +3.3%), Guidance (+2, +7.3%). Within Technology, the next-closest same-direction peer is SMCI at +19 — well below ACN's +16, so ACN is the cleaner calls expression. The suggested calls sit ~11.9% OTM with 49d to expiry, delta 0.31, mid $5.70 — well inside the 5-25% OTM / Δ 0.15-0.40 / ≤$35 premium criteria."},{"symbol":"TSEM","side":"call","total":16,"score":16,"conviction":16,"compositeScore":7.072,"recommendation":{"tier":"strong-call","label":"Strong Call","side":"call","conviction":"Very High","sizing":"Full size"},"pillars":{"fundamentals":{"score":9,"signals":[{"key":"earningsSurprise","label":"Earnings Surprise","score":3,"value":"+15.7%","note":"2026-03-31 — actual 0.65 vs est 0.562","available":true},{"key":"epsGrowth","label":"EPS Growth YoY","score":1,"value":"+62.9%","note":"","available":true},{"key":"revGrowth","label":"Revenue Growth YoY","score":1,"value":"+15.5%","note":"","available":true},{"key":"analystTarget","label":"Analyst Price Target","score":1,"value":"+13% to $313.83","note":"6 analysts","available":true},{"key":"peVsSector","label":"P/E vs Sector","score":0,"value":"128.3","note":"240% of sector median (128.3 vs 53.4)","available":true},{"key":"guidance","label":"Guidance","score":3,"value":"+45.9%","note":"+45.9% FY EPS growth est — raised proxy","available":true},{"key":"majorContract","label":"Major Contract","score":0,"value":null,"note":"no structured contract data — manual check","available":false}]},"technicals":{"score":1,"signals":[{"key":"rsi","label":"RSI 14","score":0,"value":"64.0","note":"neutral range, flat momentum","available":true},{"key":"macd","label":"MACD","score":1,"value":"1.85","note":"line above signal — bullish","available":true},{"key":"streak","label":"Streak","score":0,"value":"1d green","note":"+0.2% cumulative","available":true},{"key":"sr","label":"Support/Resistance","score":0,"value":null,"note":"between S/R levels","available":true},{"key":"fiftyTwoWeek","label":"52-Week High/Low","score":0,"value":"91% of range","note":"range $37.48–$302.86","available":true},{"key":"volConf","label":"Volume Confirmation","score":0,"value":"0.30x","note":"no S/R breakout to confirm","available":true}]},"mechanicals":{"score":0,"signals":[{"key":"unusualFlow","label":"Unusual Flow","score":0,"value":null,"note":"no unusual flow today","available":false},{"key":"oi","label":"Open Interest (C/P)","score":0,"value":"1.49x C/P","note":"42,396 calls vs 28,481 puts","available":true},{"key":"shortInterest","label":"Short Interest %","score":-1,"value":"2.9%","note":"2.9% short — complacent / shorts already covered","available":true},{"key":"unusualVolume","label":"Unusual Volume","score":0,"value":"0.30x","note":"0.30x vs 20D avg","available":true},{"key":"spyFlows","label":"SPY flows","score":1,"value":"+0.47%","note":"SPY +0.47% — risk-on tape","available":true}]},"narrative":{"score":6,"signals":[{"key":"positiveCatalyst","label":"Positive Catalyst","score":3,"value":"bullish","note":"news sentiment bullish","available":true},{"key":"sectorNarrative","label":"Sector Narrative","score":2,"value":"tailwind","note":"rides \"Semiconductors AI Demand\" (str 90)","available":true},{"key":"socialSentiment","label":"Social Sentiment","score":0,"value":null,"note":"insufficient social messages","available":false},{"key":"media","label":"Media Coverage","score":1,"value":"5 headlines","note":"5 headlines with bullish tilt","available":true},{"key":"negativeCatalyst","label":"Negative Catalyst","score":0,"value":null,"note":"no negative catalyst flagged","available":true},{"key":"macro","label":"Macro Tail/Headwinds","score":0,"value":null,"note":"no active macro narrative","available":true}]}},"thesis":"Bullish setup on TSEM: Earnings Surprise (+15.7%) — 2026-03-31 — actual 0.65 vs est 0.562; Guidance (+45.9%) — +45.9% FY EPS growth est — raised proxy; Positive Catalyst (bullish) — news sentiment bullish; Sector Narrative (tailwind) — rides \"Semiconductors AI Demand\" (str 90); EPS Growth YoY (+62.9%); Revenue Growth YoY (+15.5%); Analyst Price Target (+13% to $313.83) — 6 analysts; MACD (1.85) — line above signal — bullish.","drivers":[{"tag":"fundamentals","weight":3,"text":"Earnings Surprise (+15.7%) — 2026-03-31 — actual 0.65 vs est 0.562"},{"tag":"fundamentals","weight":3,"text":"Guidance (+45.9%) — +45.9% FY EPS growth est — raised proxy"},{"tag":"narrative","weight":3,"text":"Positive Catalyst (bullish) — news sentiment bullish"},{"tag":"narrative","weight":2,"text":"Sector Narrative (tailwind) — rides \"Semiconductors AI Demand\" (str 90)"},{"tag":"fundamentals","weight":1,"text":"EPS Growth YoY (+62.9%)"},{"tag":"fundamentals","weight":1,"text":"Revenue Growth YoY (+15.5%)"},{"tag":"fundamentals","weight":1,"text":"Analyst Price Target (+13% to $313.83) — 6 analysts"},{"tag":"technicals","weight":1,"text":"MACD (1.85) — line above signal — bullish"}],"spot":278.405,"sector":"Technology","sentiment":"bullish","fundamentalsVerdict":"mixed","rsi":64.02,"ivPctile":91,"streak":{"color":"green","days":1,"cumulativePct":0.22138673654835536},"peers":[{"symbol":"SMCI","total":19,"side":"call","tier":"strong-call","label":"Strong Call"},{"symbol":"ORCL","total":17,"side":"call","tier":"strong-call","label":"Strong Call"},{"symbol":"LRCX","total":17,"side":"call","tier":"strong-call","label":"Strong Call"},{"symbol":"TSM","total":16,"side":"call","tier":"strong-call","label":"Strong Call"},{"symbol":"ACN","total":16,"side":"call","tier":"strong-call","label":"Strong Call"}],"contract":{"strike":320,"expiry":1784246400,"expiryLabel":"Jul 16 '26","dte":49,"bid":20.2,"ask":22.5,"mid":21.35,"last":19.42,"iv":0.8712,"oi":125,"volume":1,"delta":0.399,"thetaDay":-0.3601,"breakeven":341.35,"breakevenMovePct":22.61,"expectedMovePct":32.03,"rrRatio":0.71,"extrinsicRatio":1,"earningsInWindow":false,"otmPct":14.94,"contractQuality":{"spread":{"cls":"fair","label":"OK"},"oi":{"cls":"fair","label":"Light"},"delta":{"cls":"fair","label":"Skewed"},"theta":{"cls":"fair","label":"Normal"},"iv":{"cls":"bad","label":"Elevated"},"overall":"fair"},"qualityScore":0.442},"analysis":"TSEM scores +16 — a Strong Call recommendation. The bullish read is led by Fundamentals (+9), reinforced by Narrative (+6). The biggest contributors are Earnings Surprise (+3, +15.7%), Guidance (+3, +45.9%), Positive Catalyst (+3, bullish). Cutting the other way: Short Interest % (-1, 2.9%). Within Technology, the next-closest same-direction peer is SMCI at +19 — well below TSEM's +16, so TSEM is the cleaner calls expression. The suggested calls sit ~14.9% OTM with 49d to expiry, delta 0.40, mid $21.35 — well inside the 5-25% OTM / Δ 0.15-0.40 / ≤$35 premium criteria."}]}