{"scannedAt":"2026-05-18T21:00:23.026Z","marketState":"POST","summary":{"tickerCount":3,"contractCount":5,"hottestDelta":11084,"scanned":68,"failed":0,"hadPrior":true},"tickers":[{"symbol":"PLTR","spot":135.14,"topDelta":11084,"contracts":[{"symbol":"PLTR","side":"call","strike":143,"expSec":1779408000,"vol":13263,"oi":4039,"last":0.68,"bid":0.66,"ask":0.69,"iv":0.49170430175781255,"prevVol":2179,"deltaVol":11084,"otmPct":0.058,"dte":3,"premium":901884,"tape":"ask","scannedAt":"2026-05-18T21:00:23.026Z","repeatCount":1,"firstSeen":"2026-05-18T21:00:23.026Z"}]},{"symbol":"NVDA","spot":222.32,"topDelta":7115,"contracts":[{"symbol":"NVDA","side":"put","strike":200,"expSec":1779408000,"vol":27781,"oi":15189,"last":0.96,"bid":0.95,"ask":0.96,"iv":0.7128934960937501,"prevVol":20666,"deltaVol":7115,"otmPct":0.096,"dte":3,"premium":2666976,"tape":"ask","scannedAt":"2026-05-18T19:37:46.666Z","repeatCount":3,"firstSeen":"2026-05-18T19:00:30.429Z"},{"symbol":"NVDA","side":"call","strike":260,"expSec":1779408000,"vol":13555,"oi":10802,"last":0.48,"bid":0.45,"ask":0.47,"iv":0.8256853369140623,"prevVol":9016,"deltaVol":4539,"otmPct":0.175,"dte":3,"premium":650640,"tape":"ask","scannedAt":"2026-05-18T19:37:46.666Z","repeatCount":1,"firstSeen":"2026-05-18T19:37:46.666Z"},{"symbol":"NVDA","side":"put","strike":130,"expSec":1779408000,"vol":4112,"oi":3737,"last":0.03,"bid":0.01,"ask":0.02,"iv":1.5625021874999998,"prevVol":109,"deltaVol":4003,"otmPct":0.415,"dte":3,"premium":12336,"tape":"ask","scannedAt":"2026-05-18T21:00:23.026Z","repeatCount":1,"firstSeen":"2026-05-18T21:00:23.026Z"}]},{"symbol":"MU","spot":681.54,"topDelta":5548,"contracts":[{"symbol":"MU","side":"put","strike":630,"expSec":1779408000,"vol":8960,"oi":1958,"last":11.56,"bid":11.5,"ask":11.8,"iv":1.007024007873535,"prevVol":3412,"deltaVol":5548,"otmPct":0.076,"dte":3,"premium":10357760,"tape":"blw","scannedAt":"2026-05-18T21:00:23.026Z","repeatCount":1,"firstSeen":"2026-05-18T21:00:23.026Z"}]}]}