{"scannedAt":"2026-05-26T19:00:20.792Z","etDate":"2026-05-26","etMin":330,"marketState":"REGULAR","summary":{"tickerCount":43,"hourlyFlagCount":36,"eodFlagCount":0,"srBreakCount":22},"tickers":[{"symbol":"LUNR","spot":31.7001,"avg20":12307700,"bucketHits":[{"bucketLabel":"9:30-10:30","actualHourVol":894925,"expectedHourVol":461539,"volRatio":1.94,"priceMovePct":-2.78,"hourlyFlagged":true,"moveClass":{"conviction":"High","action":"Important Move"},"srBreak":null,"scannedAt":"2026-05-26T14:28:33.046Z"},{"bucketLabel":"11:30-12:30","actualHourVol":2715729,"expectedHourVol":1353847,"volRatio":2.01,"priceMovePct":-0.11,"hourlyFlagged":true,"moveClass":{"conviction":"Medium","action":"Watch"},"srBreak":null,"scannedAt":"2026-05-26T16:00:26.215Z"},{"bucketLabel":"14:30-16:00","actualHourVol":16714347,"expectedHourVol":3076925,"volRatio":5.43,"priceMovePct":-27.72,"hourlyFlagged":true,"moveClass":{"conviction":"High","action":"Important Move"},"srBreak":null,"scannedAt":"2026-05-26T19:00:20.792Z"}],"eod":null,"scannedAt":"2026-05-26T19:00:20.792Z"},{"symbol":"RDW","spot":21.8175,"avg20":38226445,"bucketHits":[{"bucketLabel":"9:30-10:30","actualHourVol":3807181,"expectedHourVol":1433492,"volRatio":2.66,"priceMovePct":-2.41,"hourlyFlagged":true,"moveClass":{"conviction":"High","action":"Important Move"},"srBreak":null,"scannedAt":"2026-05-26T14:28:33.046Z"},{"bucketLabel":"10:30-11:30","actualHourVol":6719934,"expectedHourVol":5351702,"volRatio":1.26,"priceMovePct":2.29,"hourlyFlagged":true,"moveClass":{"conviction":"High","action":"Important Move"},"srBreak":null,"scannedAt":"2026-05-26T15:00:25.526Z"},{"bucketLabel":"11:30-12:30","actualHourVol":8934009,"expectedHourVol":4204909,"volRatio":2.12,"priceMovePct":-1.24,"hourlyFlagged":true,"moveClass":{"conviction":"High","action":"Important Move"},"srBreak":null,"scannedAt":"2026-05-26T16:00:26.215Z"},{"bucketLabel":"12:30-13:30","actualHourVol":5902675,"expectedHourVol":4204909,"volRatio":1.4,"priceMovePct":2.13,"hourlyFlagged":true,"moveClass":{"conviction":"High","action":"Important Move"},"srBreak":null,"scannedAt":"2026-05-26T17:00:21.952Z"},{"bucketLabel":"14:30-16:00","actualHourVol":11894387,"expectedHourVol":9556611,"volRatio":1.24,"priceMovePct":-3.38,"hourlyFlagged":true,"moveClass":{"conviction":"High","action":"Important Move"},"srBreak":null,"scannedAt":"2026-05-26T19:00:20.792Z"}],"eod":null,"scannedAt":"2026-05-26T19:00:20.792Z"},{"symbol":"ASTS","spot":125.8758,"avg20":21065085,"bucketHits":[{"bucketLabel":"9:30-10:30","actualHourVol":1203941,"expectedHourVol":789941,"volRatio":1.52,"priceMovePct":-1.47,"hourlyFlagged":true,"moveClass":{"conviction":"High","action":"Important Move"},"srBreak":null,"scannedAt":"2026-05-26T14:28:33.046Z"},{"bucketLabel":"10:30-11:30","actualHourVol":4316975,"expectedHourVol":2949112,"volRatio":1.46,"priceMovePct":2.22,"hourlyFlagged":true,"moveClass":{"conviction":"High","action":"Important Move"},"srBreak":{"type":"upper","level":124.01,"conviction":"Very High","action":"Strong Bullish Alert"},"scannedAt":"2026-05-26T15:00:25.526Z"},{"bucketLabel":"11:30-12:30","actualHourVol":5941409,"expectedHourVol":2317159,"volRatio":2.56,"priceMovePct":-2.72,"hourlyFlagged":true,"moveClass":{"conviction":"High","action":"Important Move"},"srBreak":null,"scannedAt":"2026-05-26T16:00:26.215Z"},{"bucketLabel":"12:30-13:30","actualHourVol":3622170,"expectedHourVol":2317159,"volRatio":1.56,"priceMovePct":2.87,"hourlyFlagged":true,"moveClass":{"conviction":"High","action":"Important Move"},"srBreak":null,"scannedAt":"2026-05-26T17:00:21.952Z"}],"eod":null,"scannedAt":"2026-05-26T17:00:21.952Z"},{"symbol":"INTU","spot":303.86,"avg20":4181110,"bucketHits":[{"bucketLabel":"9:30-10:30","actualHourVol":191676,"expectedHourVol":156792,"volRatio":1.22,"priceMovePct":-1.18,"hourlyFlagged":true,"moveClass":{"conviction":"Medium","action":"Watch"},"srBreak":null,"scannedAt":"2026-05-26T14:28:33.046Z"},{"bucketLabel":"11:30-12:30","actualHourVol":926078,"expectedHourVol":459922,"volRatio":2.01,"priceMovePct":0.39,"hourlyFlagged":true,"moveClass":{"conviction":"Medium","action":"Watch"},"srBreak":null,"scannedAt":"2026-05-26T16:00:26.215Z"},{"bucketLabel":"12:30-13:30","actualHourVol":650967,"expectedHourVol":459922,"volRatio":1.42,"priceMovePct":-0.8,"hourlyFlagged":true,"moveClass":{"conviction":"Medium","action":"Watch"},"srBreak":null,"scannedAt":"2026-05-26T17:00:21.952Z"},{"bucketLabel":"13:30-14:30","actualHourVol":1442156,"expectedHourVol":585355,"volRatio":2.46,"priceMovePct":-1.15,"hourlyFlagged":true,"moveClass":{"conviction":"Medium","action":"Watch"},"srBreak":null,"scannedAt":"2026-05-26T18:00:21.730Z"}],"eod":null,"scannedAt":"2026-05-26T18:00:21.730Z"},{"symbol":"MDB","spot":309.63,"avg20":1615025,"bucketHits":[{"bucketLabel":"9:30-10:30","actualHourVol":144864,"expectedHourVol":60563,"volRatio":2.39,"priceMovePct":-2.04,"hourlyFlagged":true,"moveClass":{"conviction":"High","action":"Important Move"},"srBreak":null,"scannedAt":"2026-05-26T14:28:33.046Z"},{"bucketLabel":"11:30-12:30","actualHourVol":278354,"expectedHourVol":177653,"volRatio":1.57,"priceMovePct":-1.27,"hourlyFlagged":true,"moveClass":{"conviction":"High","action":"Important Move"},"srBreak":null,"scannedAt":"2026-05-26T16:00:26.215Z"},{"bucketLabel":"12:30-13:30","actualHourVol":272337,"expectedHourVol":177653,"volRatio":1.53,"priceMovePct":0.47,"hourlyFlagged":true,"moveClass":{"conviction":"Medium","action":"Watch"},"srBreak":null,"scannedAt":"2026-05-26T17:00:21.952Z"}],"eod":null,"scannedAt":"2026-05-26T17:00:21.952Z"},{"symbol":"MP","spot":68.13,"avg20":6997790,"bucketHits":[{"bucketLabel":"12:30-13:30","actualHourVol":1059460,"expectedHourVol":769757,"volRatio":1.38,"priceMovePct":3.89,"hourlyFlagged":true,"moveClass":{"conviction":"High","action":"Important Move"},"srBreak":null,"scannedAt":"2026-05-26T17:00:21.952Z"},{"bucketLabel":"13:30-14:30","actualHourVol":2162157,"expectedHourVol":979691,"volRatio":2.21,"priceMovePct":2.68,"hourlyFlagged":true,"moveClass":{"conviction":"High","action":"Important Move"},"srBreak":null,"scannedAt":"2026-05-26T18:00:21.730Z"}],"eod":null,"scannedAt":"2026-05-26T18:00:21.730Z"},{"symbol":"OKTA","spot":95.3,"avg20":2751915,"bucketHits":[{"bucketLabel":"11:30-12:30","actualHourVol":647684,"expectedHourVol":302711,"volRatio":2.14,"priceMovePct":1.54,"hourlyFlagged":true,"moveClass":{"conviction":"High","action":"Important Move"},"srBreak":{"type":"upper","level":94.97,"conviction":"Very High","action":"Strong Bullish Alert"},"scannedAt":"2026-05-26T16:00:26.215Z"},{"bucketLabel":"12:30-13:30","actualHourVol":395521,"expectedHourVol":302711,"volRatio":1.31,"priceMovePct":-0.45,"hourlyFlagged":true,"moveClass":{"conviction":"Medium","action":"Watch"},"srBreak":null,"scannedAt":"2026-05-26T17:00:21.952Z"}],"eod":null,"scannedAt":"2026-05-26T17:00:21.952Z"},{"symbol":"AMKR","spot":73.13,"avg20":5344325,"bucketHits":[{"bucketLabel":"9:30-10:30","actualHourVol":286874,"expectedHourVol":200412,"volRatio":1.43,"priceMovePct":0.67,"hourlyFlagged":true,"moveClass":{"conviction":"Medium","action":"Watch"},"srBreak":null,"scannedAt":"2026-05-26T14:28:33.046Z"},{"bucketLabel":"11:30-12:30","actualHourVol":1167664,"expectedHourVol":587876,"volRatio":1.99,"priceMovePct":-1.84,"hourlyFlagged":true,"moveClass":{"conviction":"High","action":"Important Move"},"srBreak":null,"scannedAt":"2026-05-26T16:00:26.215Z"}],"eod":null,"scannedAt":"2026-05-26T16:00:26.215Z"},{"symbol":"ZS","spot":189.42,"avg20":3088700,"bucketHits":[{"bucketLabel":"9:30-10:30","actualHourVol":180979,"expectedHourVol":115826,"volRatio":1.56,"priceMovePct":-0.39,"hourlyFlagged":true,"moveClass":{"conviction":"Medium","action":"Watch"},"srBreak":null,"scannedAt":"2026-05-26T14:28:33.046Z"},{"bucketLabel":"10:30-11:30","actualHourVol":370758,"expectedHourVol":432418,"volRatio":0.86,"priceMovePct":0.66,"hourlyFlagged":false,"moveClass":{"conviction":"None","action":"Ignore"},"srBreak":{"type":"upper","level":186.99,"conviction":"None","action":"No confirmation"},"scannedAt":"2026-05-26T15:00:25.526Z"},{"bucketLabel":"11:30-12:30","actualHourVol":647933,"expectedHourVol":339757,"volRatio":1.91,"priceMovePct":-0.12,"hourlyFlagged":true,"moveClass":{"conviction":"Medium","action":"Watch"},"srBreak":null,"scannedAt":"2026-05-26T16:00:26.215Z"},{"bucketLabel":"12:30-13:30","actualHourVol":563766,"expectedHourVol":339757,"volRatio":1.66,"priceMovePct":0.92,"hourlyFlagged":true,"moveClass":{"conviction":"Medium","action":"Watch"},"srBreak":null,"scannedAt":"2026-05-26T17:00:21.952Z"},{"bucketLabel":"13:30-14:30","actualHourVol":610965,"expectedHourVol":432418,"volRatio":1.41,"priceMovePct":-0.04,"hourlyFlagged":true,"moveClass":{"conviction":"Medium","action":"Watch"},"srBreak":null,"scannedAt":"2026-05-26T18:00:21.730Z"}],"eod":null,"scannedAt":"2026-05-26T18:00:21.730Z"},{"symbol":"PL","spot":50.31,"avg20":8908140,"bucketHits":[{"bucketLabel":"9:30-10:30","actualHourVol":597397,"expectedHourVol":334055,"volRatio":1.79,"priceMovePct":-2.23,"hourlyFlagged":true,"moveClass":{"conviction":"High","action":"Important Move"},"srBreak":null,"scannedAt":"2026-05-26T14:28:33.046Z"},{"bucketLabel":"10:30-11:30","actualHourVol":1398900,"expectedHourVol":1247140,"volRatio":1.12,"priceMovePct":1.61,"hourlyFlagged":false,"moveClass":{"conviction":"None","action":"Ignore"},"srBreak":{"type":"upper","level":49.48,"conviction":"Medium","action":"Watch / Weak Break"},"scannedAt":"2026-05-26T15:00:25.526Z"},{"bucketLabel":"11:30-12:30","actualHourVol":1681646,"expectedHourVol":979895,"volRatio":1.72,"priceMovePct":0.15,"hourlyFlagged":true,"moveClass":{"conviction":"Medium","action":"Watch"},"srBreak":null,"scannedAt":"2026-05-26T16:00:26.215Z"}],"eod":null,"scannedAt":"2026-05-26T16:00:26.215Z"},{"symbol":"MRVL","spot":206.5166,"avg20":23494460,"bucketHits":[{"bucketLabel":"11:30-12:30","actualHourVol":4623006,"expectedHourVol":2584391,"volRatio":1.79,"priceMovePct":-2.2,"hourlyFlagged":true,"moveClass":{"conviction":"High","action":"Important Move"},"srBreak":null,"scannedAt":"2026-05-26T16:00:26.215Z"},{"bucketLabel":"12:30-13:30","actualHourVol":3761928,"expectedHourVol":2584391,"volRatio":1.46,"priceMovePct":3.01,"hourlyFlagged":true,"moveClass":{"conviction":"High","action":"Important Move"},"srBreak":null,"scannedAt":"2026-05-26T17:00:21.952Z"}],"eod":null,"scannedAt":"2026-05-26T17:00:21.952Z"},{"symbol":"KULR","spot":4.48,"avg20":2607050,"bucketHits":[{"bucketLabel":"11:30-12:30","actualHourVol":506461,"expectedHourVol":286776,"volRatio":1.77,"priceMovePct":-3.24,"hourlyFlagged":true,"moveClass":{"conviction":"High","action":"Important Move"},"srBreak":null,"scannedAt":"2026-05-26T16:00:26.215Z"}],"eod":null,"scannedAt":"2026-05-26T16:00:26.215Z"},{"symbol":"SNOW","spot":177.92,"avg20":7051080,"bucketHits":[{"bucketLabel":"10:30-11:30","actualHourVol":1228256,"expectedHourVol":987151,"volRatio":1.24,"priceMovePct":1.62,"hourlyFlagged":true,"moveClass":{"conviction":"High","action":"Important Move"},"srBreak":null,"scannedAt":"2026-05-26T15:00:25.526Z"},{"bucketLabel":"11:30-12:30","actualHourVol":1346827,"expectedHourVol":775619,"volRatio":1.74,"priceMovePct":-0.91,"hourlyFlagged":true,"moveClass":{"conviction":"Medium","action":"Watch"},"srBreak":null,"scannedAt":"2026-05-26T16:00:26.215Z"}],"eod":null,"scannedAt":"2026-05-26T16:00:26.215Z"},{"symbol":"VST","spot":164.895,"avg20":5776720,"bucketHits":[{"bucketLabel":"11:30-12:30","actualHourVol":1048431,"expectedHourVol":635439,"volRatio":1.65,"priceMovePct":-0.55,"hourlyFlagged":true,"moveClass":{"conviction":"Medium","action":"Watch"},"srBreak":null,"scannedAt":"2026-05-26T16:00:26.215Z"}],"eod":null,"scannedAt":"2026-05-26T16:00:26.215Z"},{"symbol":"UVXY","spot":31.48,"avg20":8873895,"bucketHits":[{"bucketLabel":"11:30-12:30","actualHourVol":1544229,"expectedHourVol":976128,"volRatio":1.58,"priceMovePct":0.64,"hourlyFlagged":true,"moveClass":{"conviction":"Medium","action":"Watch"},"srBreak":null,"scannedAt":"2026-05-26T16:00:26.215Z"}],"eod":null,"scannedAt":"2026-05-26T16:00:26.215Z"},{"symbol":"UBS","spot":47.7,"avg20":2430020,"bucketHits":[{"bucketLabel":"11:30-12:30","actualHourVol":422477,"expectedHourVol":267302,"volRatio":1.58,"priceMovePct":0.19,"hourlyFlagged":true,"moveClass":{"conviction":"Medium","action":"Watch"},"srBreak":null,"scannedAt":"2026-05-26T16:00:26.215Z"}],"eod":null,"scannedAt":"2026-05-26T16:00:26.215Z"},{"symbol":"PLAB","spot":54.11,"avg20":757000,"bucketHits":[{"bucketLabel":"9:30-10:30","actualHourVol":43625,"expectedHourVol":28388,"volRatio":1.54,"priceMovePct":0.26,"hourlyFlagged":true,"moveClass":{"conviction":"Medium","action":"Watch"},"srBreak":null,"scannedAt":"2026-05-26T14:28:33.046Z"},{"bucketLabel":"11:30-12:30","actualHourVol":126604,"expectedHourVol":83270,"volRatio":1.52,"priceMovePct":0.06,"hourlyFlagged":true,"moveClass":{"conviction":"Medium","action":"Watch"},"srBreak":null,"scannedAt":"2026-05-26T16:00:26.215Z"}],"eod":null,"scannedAt":"2026-05-26T16:00:26.215Z"},{"symbol":"DELL","spot":301.98,"avg20":6278950,"bucketHits":[{"bucketLabel":"9:30-10:30","actualHourVol":359506,"expectedHourVol":235461,"volRatio":1.53,"priceMovePct":-1.12,"hourlyFlagged":true,"moveClass":{"conviction":"Medium","action":"Watch"},"srBreak":null,"scannedAt":"2026-05-26T14:28:33.046Z"},{"bucketLabel":"11:30-12:30","actualHourVol":889540,"expectedHourVol":690685,"volRatio":1.29,"priceMovePct":-0.92,"hourlyFlagged":true,"moveClass":{"conviction":"Medium","action":"Watch"},"srBreak":null,"scannedAt":"2026-05-26T16:00:26.215Z"}],"eod":null,"scannedAt":"2026-05-26T16:00:26.215Z"},{"symbol":"APP","spot":510.38,"avg20":4633865,"bucketHits":[{"bucketLabel":"11:30-12:30","actualHourVol":780037,"expectedHourVol":509725,"volRatio":1.53,"priceMovePct":-1.8,"hourlyFlagged":true,"moveClass":{"conviction":"High","action":"Important Move"},"srBreak":null,"scannedAt":"2026-05-26T16:00:26.215Z"},{"bucketLabel":"12:30-13:30","actualHourVol":645393,"expectedHourVol":509725,"volRatio":1.27,"priceMovePct":-2.09,"hourlyFlagged":true,"moveClass":{"conviction":"High","action":"Important Move"},"srBreak":null,"scannedAt":"2026-05-26T17:00:21.952Z"}],"eod":null,"scannedAt":"2026-05-26T17:00:21.952Z"},{"symbol":"SMH","spot":593.75,"avg20":10099295,"bucketHits":[{"bucketLabel":"9:30-10:30","actualHourVol":539218,"expectedHourVol":378724,"volRatio":1.42,"priceMovePct":0.33,"hourlyFlagged":true,"moveClass":{"conviction":"Medium","action":"Watch"},"srBreak":null,"scannedAt":"2026-05-26T14:28:33.046Z"},{"bucketLabel":"11:30-12:30","actualHourVol":1594898,"expectedHourVol":1110922,"volRatio":1.44,"priceMovePct":-1.24,"hourlyFlagged":true,"moveClass":{"conviction":"High","action":"Important Move"},"srBreak":null,"scannedAt":"2026-05-26T16:00:26.215Z"}],"eod":null,"scannedAt":"2026-05-26T16:00:26.215Z"},{"symbol":"U","spot":27.125,"avg20":10785810,"bucketHits":[{"bucketLabel":"11:30-12:30","actualHourVol":1704888,"expectedHourVol":1186439,"volRatio":1.44,"priceMovePct":-0.9,"hourlyFlagged":true,"moveClass":{"conviction":"Medium","action":"Watch"},"srBreak":null,"scannedAt":"2026-05-26T16:00:26.215Z"}],"eod":null,"scannedAt":"2026-05-26T16:00:26.215Z"},{"symbol":"SMCI","spot":37.6725,"avg20":38189000,"bucketHits":[{"bucketLabel":"10:30-11:30","actualHourVol":3876357,"expectedHourVol":5346460,"volRatio":0.73,"priceMovePct":1.17,"hourlyFlagged":false,"moveClass":{"conviction":"None","action":"Ignore"},"srBreak":{"type":"upper","level":36.37,"conviction":"None","action":"No confirmation"},"scannedAt":"2026-05-26T15:00:25.526Z"},{"bucketLabel":"12:30-13:30","actualHourVol":6045464,"expectedHourVol":4200790,"volRatio":1.44,"priceMovePct":3.54,"hourlyFlagged":true,"moveClass":{"conviction":"High","action":"Important Move"},"srBreak":{"type":"upper","level":36.77,"conviction":"Very High","action":"Strong Bullish Alert"},"scannedAt":"2026-05-26T17:00:21.952Z"}],"eod":null,"scannedAt":"2026-05-26T17:00:21.952Z"},{"symbol":"DRAM","spot":60.7501,"avg20":32335065,"bucketHits":[{"bucketLabel":"9:30-10:30","actualHourVol":1729512,"expectedHourVol":1212565,"volRatio":1.43,"priceMovePct":0.78,"hourlyFlagged":true,"moveClass":{"conviction":"Medium","action":"Watch"},"srBreak":{"type":"upper","level":59.28,"conviction":"None","action":"No confirmation"},"scannedAt":"2026-05-26T14:28:33.046Z"},{"bucketLabel":"11:30-12:30","actualHourVol":5102506,"expectedHourVol":3556857,"volRatio":1.43,"priceMovePct":0.41,"hourlyFlagged":true,"moveClass":{"conviction":"Medium","action":"Watch"},"srBreak":null,"scannedAt":"2026-05-26T16:00:26.215Z"},{"bucketLabel":"13:30-14:30","actualHourVol":3103181,"expectedHourVol":4526909,"volRatio":0.69,"priceMovePct":0.84,"hourlyFlagged":false,"moveClass":{"conviction":"None","action":"Ignore"},"srBreak":{"type":"upper","level":60.32,"conviction":"None","action":"No confirmation"},"scannedAt":"2026-05-26T18:00:21.730Z"},{"bucketLabel":"14:30-16:00","actualHourVol":3186662,"expectedHourVol":8083766,"volRatio":0.39,"priceMovePct":0.41,"hourlyFlagged":false,"moveClass":{"conviction":"None","action":"Ignore"},"srBreak":{"type":"upper","level":60.58,"conviction":"None","action":"No confirmation"},"scannedAt":"2026-05-26T19:00:20.792Z"}],"eod":null,"scannedAt":"2026-05-26T19:00:20.792Z"},{"symbol":"WMT","spot":118.32,"avg20":19179305,"bucketHits":[{"bucketLabel":"11:30-12:30","actualHourVol":2996445,"expectedHourVol":2109724,"volRatio":1.42,"priceMovePct":-0.01,"hourlyFlagged":true,"moveClass":{"conviction":"Medium","action":"Watch"},"srBreak":null,"scannedAt":"2026-05-26T16:00:26.215Z"},{"bucketLabel":"13:30-14:30","actualHourVol":2319159,"expectedHourVol":2685103,"volRatio":0.86,"priceMovePct":-0.21,"hourlyFlagged":false,"moveClass":{"conviction":"None","action":"Ignore"},"srBreak":{"type":"lower","level":118.41,"conviction":"None","action":"No confirmation"},"scannedAt":"2026-05-26T18:00:21.730Z"}],"eod":null,"scannedAt":"2026-05-26T18:00:21.730Z"},{"symbol":"COST","spot":1003.2748,"avg20":1942055,"bucketHits":[{"bucketLabel":"11:30-12:30","actualHourVol":300995,"expectedHourVol":213626,"volRatio":1.41,"priceMovePct":0.46,"hourlyFlagged":true,"moveClass":{"conviction":"Medium","action":"Watch"},"srBreak":null,"scannedAt":"2026-05-26T16:00:26.215Z"}],"eod":null,"scannedAt":"2026-05-26T16:00:26.215Z"},{"symbol":"RKLB","spot":141.61,"avg20":27765260,"bucketHits":[{"bucketLabel":"11:30-12:30","actualHourVol":4298470,"expectedHourVol":3054179,"volRatio":1.41,"priceMovePct":-0.94,"hourlyFlagged":true,"moveClass":{"conviction":"Medium","action":"Watch"},"srBreak":null,"scannedAt":"2026-05-26T16:00:26.215Z"}],"eod":null,"scannedAt":"2026-05-26T16:00:26.215Z"},{"symbol":"MU","spot":905.64,"avg20":50849105,"bucketHits":[{"bucketLabel":"9:30-10:30","actualHourVol":2655824,"expectedHourVol":1906841,"volRatio":1.39,"priceMovePct":1.63,"hourlyFlagged":true,"moveClass":{"conviction":"High","action":"Important Move"},"srBreak":null,"scannedAt":"2026-05-26T14:28:33.046Z"},{"bucketLabel":"11:30-12:30","actualHourVol":7266729,"expectedHourVol":5593402,"volRatio":1.3,"priceMovePct":-0.55,"hourlyFlagged":true,"moveClass":{"conviction":"Medium","action":"Watch"},"srBreak":null,"scannedAt":"2026-05-26T16:00:26.215Z"},{"bucketLabel":"13:30-14:30","actualHourVol":6858467,"expectedHourVol":7118875,"volRatio":0.96,"priceMovePct":1.33,"hourlyFlagged":false,"moveClass":{"conviction":"Low","action":"Caution - Weak Move"},"srBreak":{"type":"upper","level":891.27,"conviction":"Medium","action":"Watch / Weak Break"},"scannedAt":"2026-05-26T18:00:21.730Z"},{"bucketLabel":"14:30-16:00","actualHourVol":7343946,"expectedHourVol":12712276,"volRatio":0.58,"priceMovePct":0.92,"hourlyFlagged":false,"moveClass":{"conviction":"None","action":"Ignore"},"srBreak":{"type":"upper","level":899.41,"conviction":"None","action":"No confirmation"},"scannedAt":"2026-05-26T19:00:20.792Z"}],"eod":null,"scannedAt":"2026-05-26T19:00:20.792Z"},{"symbol":"OKLO","spot":69.3116,"avg20":13789205,"bucketHits":[{"bucketLabel":"11:30-12:30","actualHourVol":2058196,"expectedHourVol":1516813,"volRatio":1.36,"priceMovePct":-1.22,"hourlyFlagged":true,"moveClass":{"conviction":"High","action":"Important Move"},"srBreak":null,"scannedAt":"2026-05-26T16:00:26.215Z"}],"eod":null,"scannedAt":"2026-05-26T16:00:26.215Z"},{"symbol":"NVDA","spot":213.38,"avg20":162604985,"bucketHits":[{"bucketLabel":"11:30-12:30","actualHourVol":23954813,"expectedHourVol":17886548,"volRatio":1.34,"priceMovePct":-1.09,"hourlyFlagged":true,"moveClass":{"conviction":"Medium","action":"Watch"},"srBreak":null,"scannedAt":"2026-05-26T16:00:26.215Z"}],"eod":null,"scannedAt":"2026-05-26T16:00:26.215Z"},{"symbol":"QCOM","spot":250.4,"avg20":32011625,"bucketHits":[{"bucketLabel":"10:30-11:30","actualHourVol":5897512,"expectedHourVol":4481628,"volRatio":1.32,"priceMovePct":3.46,"hourlyFlagged":true,"moveClass":{"conviction":"High","action":"Important Move"},"srBreak":{"type":"upper","level":247.9,"conviction":"Very High","action":"Strong Bullish Alert"},"scannedAt":"2026-05-26T15:00:25.526Z"}],"eod":null,"scannedAt":"2026-05-26T15:00:25.526Z"},{"symbol":"ASML","spot":1609.715,"avg20":1655715,"bucketHits":[{"bucketLabel":"11:30-12:30","actualHourVol":238246,"expectedHourVol":182129,"volRatio":1.31,"priceMovePct":-1.37,"hourlyFlagged":true,"moveClass":{"conviction":"High","action":"Important Move"},"srBreak":null,"scannedAt":"2026-05-26T16:00:26.215Z"}],"eod":null,"scannedAt":"2026-05-26T16:00:26.215Z"},{"symbol":"ALAB","spot":316.77,"avg20":6195135,"bucketHits":[{"bucketLabel":"9:30-10:30","actualHourVol":290128,"expectedHourVol":232318,"volRatio":1.25,"priceMovePct":0.94,"hourlyFlagged":true,"moveClass":{"conviction":"Medium","action":"Watch"},"srBreak":null,"scannedAt":"2026-05-26T14:28:33.046Z"},{"bucketLabel":"12:30-13:30","actualHourVol":786103,"expectedHourVol":681465,"volRatio":1.15,"priceMovePct":2.08,"hourlyFlagged":false,"moveClass":{"conviction":"None","action":"Ignore"},"srBreak":{"type":"upper","level":316.5,"conviction":"Medium","action":"Watch / Weak Break"},"scannedAt":"2026-05-26T17:00:21.952Z"}],"eod":null,"scannedAt":"2026-05-26T17:00:21.952Z"},{"symbol":"QQQ","spot":726.44,"avg20":39339335,"bucketHits":[{"bucketLabel":"11:30-12:30","actualHourVol":5281424,"expectedHourVol":4327327,"volRatio":1.22,"priceMovePct":-0.47,"hourlyFlagged":true,"moveClass":{"conviction":"Medium","action":"Watch"},"srBreak":null,"scannedAt":"2026-05-26T16:00:26.215Z"}],"eod":null,"scannedAt":"2026-05-26T16:00:26.215Z"},{"symbol":"TSEM","spot":283.25,"avg20":2458430,"bucketHits":[{"bucketLabel":"11:30-12:30","actualHourVol":330639,"expectedHourVol":270427,"volRatio":1.22,"priceMovePct":2.57,"hourlyFlagged":true,"moveClass":{"conviction":"High","action":"Important Move"},"srBreak":null,"scannedAt":"2026-05-26T16:00:26.215Z"}],"eod":null,"scannedAt":"2026-05-26T16:00:26.215Z"},{"symbol":"AVGO","spot":422.91,"avg20":18613525,"bucketHits":[{"bucketLabel":"12:30-13:30","actualHourVol":2469017,"expectedHourVol":2047488,"volRatio":1.21,"priceMovePct":0.09,"hourlyFlagged":true,"moveClass":{"conviction":"Medium","action":"Watch"},"srBreak":null,"scannedAt":"2026-05-26T17:00:21.952Z"}],"eod":null,"scannedAt":"2026-05-26T17:00:21.952Z"},{"symbol":"PLTR","spot":137.365,"avg20":40641770,"bucketHits":[{"bucketLabel":"11:30-12:30","actualHourVol":5369007,"expectedHourVol":4470595,"volRatio":1.2,"priceMovePct":0.99,"hourlyFlagged":true,"moveClass":{"conviction":"Medium","action":"Watch"},"srBreak":null,"scannedAt":"2026-05-26T16:00:26.215Z"}],"eod":null,"scannedAt":"2026-05-26T16:00:26.215Z"},{"symbol":"SNDK","spot":1602.41,"avg20":15166450,"bucketHits":[{"bucketLabel":"9:30-10:30","actualHourVol":577390,"expectedHourVol":568742,"volRatio":1.02,"priceMovePct":0.99,"hourlyFlagged":false,"moveClass":{"conviction":"None","action":"Ignore"},"srBreak":{"type":"upper","level":1600,"conviction":"None","action":"No confirmation"},"scannedAt":"2026-05-26T14:28:33.046Z"}],"eod":null,"scannedAt":"2026-05-26T14:28:33.046Z"},{"symbol":"AMD","spot":499.585,"avg20":42390425,"bucketHits":[{"bucketLabel":"12:30-13:30","actualHourVol":3347070,"expectedHourVol":4662947,"volRatio":0.72,"priceMovePct":1.7,"hourlyFlagged":false,"moveClass":{"conviction":"Low","action":"Caution - Weak Move"},"srBreak":{"type":"upper","level":496.89,"conviction":"Low","action":"Likely Fakeout"},"scannedAt":"2026-05-26T17:00:21.952Z"},{"bucketLabel":"14:30-16:00","actualHourVol":3439427,"expectedHourVol":10597606,"volRatio":0.32,"priceMovePct":0.77,"hourlyFlagged":false,"moveClass":{"conviction":"None","action":"Ignore"},"srBreak":{"type":"upper","level":498,"conviction":"None","action":"No confirmation"},"scannedAt":"2026-05-26T19:00:20.792Z"}],"eod":null,"scannedAt":"2026-05-26T19:00:20.792Z"},{"symbol":"EWY","spot":198.99,"avg20":17455720,"bucketHits":[{"bucketLabel":"9:30-10:30","actualHourVol":436034,"expectedHourVol":654590,"volRatio":0.67,"priceMovePct":0.19,"hourlyFlagged":false,"moveClass":{"conviction":"None","action":"Ignore"},"srBreak":{"type":"upper","level":198.87,"conviction":"None","action":"No confirmation"},"scannedAt":"2026-05-26T14:28:33.046Z"}],"eod":null,"scannedAt":"2026-05-26T14:28:33.046Z"},{"symbol":"IWM","spot":290.04,"avg20":26423215,"bucketHits":[{"bucketLabel":"10:30-11:30","actualHourVol":1794751,"expectedHourVol":3699250,"volRatio":0.49,"priceMovePct":0.15,"hourlyFlagged":false,"moveClass":{"conviction":"None","action":"Ignore"},"srBreak":{"type":"upper","level":289.96,"conviction":"None","action":"No confirmation"},"scannedAt":"2026-05-26T15:00:25.526Z"}],"eod":null,"scannedAt":"2026-05-26T15:00:25.526Z"},{"symbol":"FTNT","spot":134.35,"avg20":6242290,"bucketHits":[{"bucketLabel":"11:30-12:30","actualHourVol":330638,"expectedHourVol":686652,"volRatio":0.48,"priceMovePct":0.49,"hourlyFlagged":false,"moveClass":{"conviction":"None","action":"Ignore"},"srBreak":{"type":"upper","level":134.19,"conviction":"None","action":"No confirmation"},"scannedAt":"2026-05-26T16:00:26.215Z"}],"eod":null,"scannedAt":"2026-05-26T16:00:26.215Z"},{"symbol":"STX","spot":859.99,"avg20":4796400,"bucketHits":[{"bucketLabel":"13:30-14:30","actualHourVol":292688,"expectedHourVol":671496,"volRatio":0.44,"priceMovePct":1.07,"hourlyFlagged":false,"moveClass":{"conviction":"None","action":"Ignore"},"srBreak":{"type":"upper","level":852.86,"conviction":"None","action":"No confirmation"},"scannedAt":"2026-05-26T18:00:21.730Z"}],"eod":null,"scannedAt":"2026-05-26T18:00:21.730Z"},{"symbol":"AAPL","spot":311.7,"avg20":48397365,"bucketHits":[{"bucketLabel":"10:30-11:30","actualHourVol":2363564,"expectedHourVol":6775631,"volRatio":0.35,"priceMovePct":0.07,"hourlyFlagged":false,"moveClass":{"conviction":"None","action":"Ignore"},"srBreak":{"type":"upper","level":311.49,"conviction":"None","action":"No confirmation"},"scannedAt":"2026-05-26T15:00:25.526Z"}],"eod":null,"scannedAt":"2026-05-26T15:00:25.526Z"}]}